{"query":"How is the COMMAREA used for inter-program communication?","top_k_built":10,"results":[{"file_path":"/Users/ianzepp/github/gauntlet/gauntlet-week-3/aws-mainframe-modernization-carddemo/app/cpy/COCOM01Y.cpy","file_name":"COCOM01Y.cpy","file_type":"cpy","name":"COCOM01Y","start_line":1.0,"end_line":47.0,"score":0.3110198974609375,"chunk_type":"copybook","preamble":"File: COCOM01Y.cpy\nCopybook: COCOM01Y (lines 1-47)","summary":"copybook COCOM01Y in COCOM01Y.cpy. comment hint: Communication area for CardDemo application programs.","content":"      ******************************************************************\n      * Communication area for CardDemo application programs\n      ******************************************************************\n      * Copyright Amazon.com, Inc. or its affiliates.                   \n      * All Rights Reserved.                                            \n      *                                                                 \n      * Licensed under the Apache License, Version 2.0 (the \"License\"). \n      * You may not use this file except in compliance with the License.\n      * You may obtain a copy of the License at                         \n      *                                                                 \n      *    http://www.apache.org/licenses/LICENSE-2.0                   \n      *                                                                 \n      * Unless required by applicable law or agreed to in writing,      \n      * software distributed under the License is distributed on an     \n      * \"AS IS\" BASIS, WITHOUT WARRANTIES OR CONDITIONS OF ANY KIND,    \n      * either express or implied. See the License for the specific     \n      * language governing permissions and limitations under the License\n      ****************************************************************** \n       01 CARDDEMO-COMMAREA.\n          05 CDEMO-GENERAL-INFO.\n             10 CDEMO-FROM-TRANID             PIC X(04).\n             10 CDEMO-FROM-PROGRAM            PIC X(08).\n             10 CDEMO-TO-TRANID               PIC X(04).\n             10 CDEMO-TO-PROGRAM              PIC X(08).\n             10 CDEMO-USER-ID                 PIC X(08).\n             10 CDEMO-USER-TYPE               PIC X(01).\n                88 CDEMO-USRTYP-ADMIN         VALUE 'A'.\n                88 CDEMO-USRTYP-USER          VALUE 'U'.\n             10 CDEMO-PGM-CONTEXT             PIC 9(01).\n                88 CDEMO-PGM-ENTER            VALUE 0.\n                88 CDEMO-PGM-REENTER          VALUE 1.\n          05 CDEMO-CUSTOMER-INFO.\n             10 CDEMO-CUST-ID                 PIC 9(09).\n             10 CDEMO-CUST-FNAME              PIC X(25).\n             10 CDEMO-CUST-MNAME              PIC X(25).\n             10 CDEMO-CUST-LNAME              PIC X(25).\n          05 CDEMO-ACCOUNT-INFO.\n             10 CDEMO-ACCT-ID                 PIC 9(11).\n             10 CDEMO-ACCT-STATUS             PIC X(01).\n          05 CDEMO-CARD-INFO.\n             10 CDEMO-CARD-NUM                PIC 9(16).\n          05 CDEMO-MORE-INFO.\n             10  CDEMO-LAST-MAP               PIC X(7).\n             10  CDEMO-LAST-MAPSET            PIC X(7).\n      *\n      * Ver: CardDemo_v1.0-15-g27d6c6f-68 Date: 2022-07-19 23:15:57 CDT\n      *\n","comments":"\nCommunication area for CardDemo application programs\n\nCopyright Amazon.com, Inc. or its affiliates.\nAll Rights Reserved.\n\nLicensed under the Apache License, Version 2.0 (the \"License\").\nYou may not use this file except in compliance with the License.\nYou may obtain a copy of the License at\n\nhttp://www.apache.org/licenses/LICENSE-2.0\n\nUnless required by applicable law or agreed to in writing,\nsoftware distributed under the License is distributed on an\n\"AS IS\" BASIS, WITHOUT WARRANTIES OR CONDITIONS OF ANY KIND,\neither express or implied. See the License for the specific\nlanguage governing permissions and limitations under the License\n","copy_references":[],"calls_to":[]},{"file_path":"/Users/ianzepp/github/gauntlet/gauntlet-week-3/aws-mainframe-modernization-carddemo/app/app-transaction-type-db2/cbl/COTRTUPC.cbl","file_name":"COTRTUPC.cbl","file_type":"cbl","name":"WS-COMMAREA","start_line":336.0,"end_line":339.0,"score":0.2752954661846161,"chunk_type":"data_division","preamble":"File: COTRTUPC.cbl\nProgram: 00220000 - Business logic                                    *00030000 - Accept and process TRANSACTION TYPE UPDATE        *00040000\nData: WS-COMMAREA (lines 336-339)","summary":"data_division WS-COMMAREA in COTRTUPC.cbl. uses COPY refs: CVCRD01Y, DFHBMSCA, DFHAID, COTTL01Y....","content":" 01  WS-COMMAREA                                 PIC X(2000).     03360000\n                                                                  03370000\n                                                                  03380000\n LINKAGE SECTION.                                                 03390000","comments":"","copy_references":["CVCRD01Y","DFHBMSCA","DFHAID","COTTL01Y","COTRTUP","CSDAT01Y","CSMSG01Y","CSMSG02Y","CSUSR01Y","SQL:DCLTRTYP","SQL:DCLTRCAT","COCOM01Y","CSSETATY"],"calls_to":[]},{"file_path":"/Users/ianzepp/github/gauntlet/gauntlet-week-3/aws-mainframe-modernization-carddemo/app/cbl/COMEN01C.cbl","file_name":"COMEN01C.cbl","file_type":"cbl","name":"DATA DIVISION","start_line":29.0,"end_line":73.0,"score":0.2747618854045868,"chunk_type":"data_division","preamble":"File: COMEN01C.cbl\nProgram: COMEN01C - CICS COBOL Program - Main Menu for the Regular users\nSection: DATA DIVISION (lines 29-73)","summary":"data_division DATA DIVISION in COMEN01C.cbl. uses COPY refs: COCOM01Y, COMEN02Y, COMEN01, COTTL01Y....","content":"       DATA DIVISION.\n      *----------------------------------------------------------------*\n      *                     WORKING STORAGE SECTION\n      *----------------------------------------------------------------*\n       WORKING-STORAGE SECTION.\n\n       01 WS-VARIABLES.\n         05 WS-PGMNAME                 PIC X(08) VALUE 'COMEN01C'.\n         05 WS-TRANID                  PIC X(04) VALUE 'CM00'.\n         05 WS-MESSAGE                 PIC X(80) VALUE SPACES.\n         05 WS-USRSEC-FILE             PIC X(08) VALUE 'USRSEC  '.\n         05 WS-ERR-FLG                 PIC X(01) VALUE 'N'.\n           88 ERR-FLG-ON                         VALUE 'Y'.\n           88 ERR-FLG-OFF                        VALUE 'N'.\n         05 WS-RESP-CD                 PIC S9(09) COMP VALUE ZEROS.\n         05 WS-REAS-CD                 PIC S9(09) COMP VALUE ZEROS.\n         05 WS-OPTION-X                PIC X(02) JUST RIGHT.\n         05 WS-OPTION                  PIC 9(02) VALUE 0.\n         05 WS-IDX                     PIC S9(04) COMP VALUE ZEROS.\n         05 WS-MENU-OPT-TXT            PIC X(40) VALUE SPACES.\n\n       COPY COCOM01Y.\n       COPY COMEN02Y.\n\n       COPY COMEN01.\n\n       COPY COTTL01Y.\n       COPY CSDAT01Y.\n       COPY CSMSG01Y.\n       COPY CSUSR01Y.\n\n       COPY DFHAID.\n       COPY DFHBMSCA.\n\n      *----------------------------------------------------------------*\n      *                        LINKAGE SECTION\n      *----------------------------------------------------------------*\n       LINKAGE SECTION.\n       01  DFHCOMMAREA.\n         05  LK-COMMAREA                           PIC X(01)\n             OCCURS 1 TO 32767 TIMES DEPENDING ON EIBCALEN.\n\n      *----------------------------------------------------------------*\n      *                       PROCEDURE DIVISION\n      *----------------------------------------------------------------*","comments":"","copy_references":["COCOM01Y","COMEN02Y","COMEN01","COTTL01Y","CSDAT01Y","CSMSG01Y","CSUSR01Y","DFHAID","DFHBMSCA"],"calls_to":[]},{"file_path":"/Users/ianzepp/github/gauntlet/gauntlet-week-3/aws-mainframe-modernization-carddemo/app/cbl/COADM01C.cbl","file_name":"COADM01C.cbl","file_type":"cbl","name":"DATA DIVISION","start_line":29.0,"end_line":73.0,"score":0.2711888253688812,"chunk_type":"data_division","preamble":"File: COADM01C.cbl\nProgram: COADM01C - CICS COBOL Program - Admin Menu for Admin users\nSection: DATA DIVISION (lines 29-73)","summary":"data_division DATA DIVISION in COADM01C.cbl. uses COPY refs: COCOM01Y, COADM02Y, COADM01, COTTL01Y....","content":"       DATA DIVISION.                                                           \n      *----------------------------------------------------------------*        \n      *                     WORKING STORAGE SECTION                             \n      *----------------------------------------------------------------*        \n       WORKING-STORAGE SECTION.                                                 \n                                                                                \n       01 WS-VARIABLES.                                                         \n         05 WS-PGMNAME                 PIC X(08) VALUE 'COADM01C'.              \n         05 WS-TRANID                  PIC X(04) VALUE 'CA00'.                  \n         05 WS-MESSAGE                 PIC X(80) VALUE SPACES.                  \n         05 WS-USRSEC-FILE             PIC X(08) VALUE 'USRSEC  '.              \n         05 WS-ERR-FLG                 PIC X(01) VALUE 'N'.                     \n           88 ERR-FLG-ON                         VALUE 'Y'.                     \n           88 ERR-FLG-OFF                        VALUE 'N'.                     \n         05 WS-RESP-CD                 PIC S9(09) COMP VALUE ZEROS.             \n         05 WS-REAS-CD                 PIC S9(09) COMP VALUE ZEROS.             \n         05 WS-OPTION-X                PIC X(02) JUST RIGHT.                    \n         05 WS-OPTION                  PIC 9(02) VALUE 0.                       \n         05 WS-IDX                     PIC S9(04) COMP VALUE ZEROS.             \n         05 WS-ADMIN-OPT-TXT           PIC X(40) VALUE SPACES.                  \n                                                                                \n       COPY COCOM01Y.                                                           \n       COPY COADM02Y.                                                           \n                                                                                \n       COPY COADM01.                                                            \n                                                                                \n       COPY COTTL01Y.                                                           \n       COPY CSDAT01Y.                                                           \n       COPY CSMSG01Y.                                                           \n       COPY CSUSR01Y.                                                           \n                                                                                \n       COPY DFHAID.                                                             \n       COPY DFHBMSCA.                                                           \n                                                                                \n      *----------------------------------------------------------------*        \n      *                        LINKAGE SECTION                                  \n      *----------------------------------------------------------------*        \n       LINKAGE SECTION.                                                         \n       01  DFHCOMMAREA.                                                         \n         05  LK-COMMAREA                           PIC X(01)                    \n             OCCURS 1 TO 32767 TIMES DEPENDING ON EIBCALEN.                     \n                                                                                \n      *----------------------------------------------------------------*        \n      *                       PROCEDURE DIVISION                                \n      *----------------------------------------------------------------*        ","comments":"","copy_references":["COCOM01Y","COADM02Y","COADM01","COTTL01Y","CSDAT01Y","CSMSG01Y","CSUSR01Y","DFHAID","DFHBMSCA"],"calls_to":[]},{"file_path":"/Users/ianzepp/github/gauntlet/gauntlet-week-3/aws-mainframe-modernization-carddemo/app/cbl/COACTUPC.cbl","file_name":"COACTUPC.cbl","file_type":"cbl","name":"WS-COMMAREA","start_line":850.0,"end_line":853.0,"score":0.2711206078529358,"chunk_type":"data_division","preamble":"File: COACTUPC.cbl\nProgram: COACTUPC - Business logic - Accept and process ACCOUNT UPDATE\nData: WS-COMMAREA (lines 850-853)","summary":"data_division WS-COMMAREA in COACTUPC.cbl. uses COPY refs: CVCRD01Y, CSLKPCDY, DFHBMSCA, DFHAID....","content":"       01  WS-COMMAREA                                 PIC X(2000).\n\n\n       LINKAGE SECTION.","comments":"","copy_references":["CVCRD01Y","CSLKPCDY","DFHBMSCA","DFHAID","COTTL01Y","COACTUP","CSDAT01Y","CSMSG01Y","CSMSG02Y","CSUSR01Y","CVACT01Y","CVACT03Y","CVCUS01Y","COCOM01Y","CSSETATY","CSUTLDPY"],"calls_to":[]},{"file_path":"/Users/ianzepp/github/gauntlet/gauntlet-week-3/aws-mainframe-modernization-carddemo/app/cbl/COCRDSLC.cbl","file_name":"COCRDSLC.cbl","file_type":"cbl","name":"DFHCOMMAREA","start_line":243.0,"end_line":246.0,"score":0.2671443819999695,"chunk_type":"data_division","preamble":"File: COCRDSLC.cbl\nProgram: COCRDSLC - Business logic - Accept and process credit card detail request\nData: DFHCOMMAREA (lines 243-246)","summary":"data_division DFHCOMMAREA in COCRDSLC.cbl. uses COPY refs: CVCRD01Y, COCOM01Y, DFHBMSCA, DFHAID....","content":"       01  DFHCOMMAREA.                                                         \n         05  FILLER                                PIC X(1)                     \n             OCCURS 1 TO 32767 TIMES DEPENDING ON EIBCALEN.                     \n                                                                                ","comments":"","copy_references":["CVCRD01Y","COCOM01Y","DFHBMSCA","DFHAID","COTTL01Y","COCRDSL","CSDAT01Y","CSMSG01Y","CSMSG02Y","CSUSR01Y","CVACT02Y","CVCUS01Y"],"calls_to":[]},{"file_path":"/Users/ianzepp/github/gauntlet/gauntlet-week-3/aws-mainframe-modernization-carddemo/app/cbl/COMEN01C.cbl","file_name":"COMEN01C.cbl","file_type":"cbl","name":"MAIN-PARA","start_line":75.0,"end_line":114.0,"score":0.2571270167827606,"chunk_type":"paragraph","preamble":"File: COMEN01C.cbl\nProgram: COMEN01C - CICS COBOL Program - Main Menu for the Regular users\nParagraph: MAIN-PARA (lines 75-114)\nReferences: COPY COCOM01Y, COPY COMEN02Y, COPY COMEN01, COPY COTTL01Y, COPY CSDAT01Y, COPY CSMSG01Y, COPY CSUSR01Y, COPY DFHAID, COPY DFHBMSCA\nCalls: PERFORM PROCESS-ENTER-KEY, PERFORM RECEIVE-MENU-SCREEN, PERFORM RETURN-TO-SIGNON-SCREEN, PERFORM SEND-MENU-SCREEN","summary":"paragraph MAIN-PARA in COMEN01C.cbl. uses COPY refs: COCOM01Y, COMEN02Y, COMEN01, COTTL01Y.... invokes: PERFORM PROCESS-ENTER-KEY, PERFORM RECEIVE-MENU-SCREEN, PERFORM RETURN-TO-SIGNON-SCREEN, PERFORM SEND-MENU-SCREEN.","content":"       MAIN-PARA.\n\n           SET ERR-FLG-OFF TO TRUE\n\n           MOVE SPACES TO WS-MESSAGE\n                          ERRMSGO OF COMEN1AO\n\n           IF EIBCALEN = 0\n               MOVE 'COSGN00C' TO CDEMO-FROM-PROGRAM\n               PERFORM RETURN-TO-SIGNON-SCREEN\n           ELSE\n               MOVE DFHCOMMAREA(1:EIBCALEN) TO CARDDEMO-COMMAREA\n               IF NOT CDEMO-PGM-REENTER\n                   SET CDEMO-PGM-REENTER    TO TRUE\n                   MOVE LOW-VALUES          TO COMEN1AO\n                   PERFORM SEND-MENU-SCREEN\n               ELSE\n                   PERFORM RECEIVE-MENU-SCREEN\n                   EVALUATE EIBAID\n                       WHEN DFHENTER\n                           PERFORM PROCESS-ENTER-KEY\n                       WHEN DFHPF3\n                           MOVE 'COSGN00C' TO CDEMO-TO-PROGRAM\n                           PERFORM RETURN-TO-SIGNON-SCREEN\n                       WHEN OTHER\n                           MOVE 'Y'                       TO WS-ERR-FLG\n                           MOVE CCDA-MSG-INVALID-KEY      TO WS-MESSAGE\n                           PERFORM SEND-MENU-SCREEN\n                   END-EVALUATE\n               END-IF\n           END-IF\n\n           EXEC CICS RETURN\n                     TRANSID (WS-TRANID)\n                     COMMAREA (CARDDEMO-COMMAREA)\n           END-EXEC.\n\n      *----------------------------------------------------------------*\n      *                      PROCESS-ENTER-KEY\n      *----------------------------------------------------------------*","comments":"","copy_references":["COCOM01Y","COMEN02Y","COMEN01","COTTL01Y","CSDAT01Y","CSMSG01Y","CSUSR01Y","DFHAID","DFHBMSCA"],"calls_to":["PERFORM PROCESS-ENTER-KEY","PERFORM RECEIVE-MENU-SCREEN","PERFORM RETURN-TO-SIGNON-SCREEN","PERFORM SEND-MENU-SCREEN"]},{"file_path":"/Users/ianzepp/github/gauntlet/gauntlet-week-3/aws-mainframe-modernization-carddemo/app/cbl/COACTVWC.cbl","file_name":"COACTVWC.cbl","file_type":"cbl","name":"WS-COMMAREA","start_line":218.0,"end_line":256.0,"score":0.2546176314353943,"chunk_type":"data_division","preamble":"File: COACTVWC.cbl\nProgram: COACTVWC - Business logic - Accept and process Account View request\nData: WS-COMMAREA (lines 218-256)","summary":"data_division WS-COMMAREA in COACTVWC.cbl. uses COPY refs: CVCRD01Y, COCOM01Y, DFHBMSCA, DFHAID....","content":"       01  WS-COMMAREA                             PIC X(2000).                 \n                                                                                \n      *IBM SUPPLIED COPYBOOKS                                                   \n       COPY DFHBMSCA.                                                           \n       COPY DFHAID.                                                             \n                                                                                \n      *COMMON COPYBOOKS                                                         \n      *Screen Titles                                                            \n       COPY COTTL01Y.                                                           \n                                                                                \n      *BMS Copybook                                                             \n       COPY COACTVW.                                                            \n                                                                                \n      *Current Date                                                             \n       COPY CSDAT01Y.                                                           \n                                                                                \n      *Common Messages                                                          \n       COPY CSMSG01Y.                                                           \n                                                                                \n      *Abend Variables                                                          \n       COPY CSMSG02Y.                                                           \n                                                                                \n      *Signed on user data                                                      \n       COPY CSUSR01Y.                                                           \n                                                                                \n      *ACCOUNT RECORD LAYOUT                                                    \n       COPY CVACT01Y.                                                           \n                                                                                \n                                                                                \n      *CUSTOMER RECORD LAYOUT                                                   \n       COPY CVACT02Y.                                                           \n                                                                                \n      *CARD XREF LAYOUT                                                         \n       COPY CVACT03Y.                                                           \n                                                                                \n      *CUSTOMER LAYOUT                                                          \n       COPY CVCUS01Y.                                                           \n                                                                                \n       LINKAGE SECTION.                                                         ","comments":"","copy_references":["CVCRD01Y","COCOM01Y","DFHBMSCA","DFHAID","COTTL01Y","COACTVW","CSDAT01Y","CSMSG01Y","CSMSG02Y","CSUSR01Y","CVACT01Y","CVACT02Y","CVACT03Y","CVCUS01Y"],"calls_to":[]},{"file_path":"/Users/ianzepp/github/gauntlet/gauntlet-week-3/aws-mainframe-modernization-carddemo/app/app-transaction-type-db2/cbl/COTRTUPC.cbl","file_name":"COTRTUPC.cbl","file_type":"cbl","name":"DFHCOMMAREA","start_line":340.0,"end_line":343.0,"score":0.2519022524356842,"chunk_type":"data_division","preamble":"File: COTRTUPC.cbl\nProgram: 00220000 - Business logic                                    *00030000 - Accept and process TRANSACTION TYPE UPDATE        *00040000\nData: DFHCOMMAREA (lines 340-343)","summary":"data_division DFHCOMMAREA in COTRTUPC.cbl. uses COPY refs: CVCRD01Y, DFHBMSCA, DFHAID, COTTL01Y....","content":" 01  DFHCOMMAREA.                                                 03400000\n   05  FILLER                                PIC X(1)             03410000\n       OCCURS 1 TO 32767 TIMES DEPENDING ON EIBCALEN.             03420000\n                                                                  03430000","comments":"","copy_references":["CVCRD01Y","DFHBMSCA","DFHAID","COTTL01Y","COTRTUP","CSDAT01Y","CSMSG01Y","CSMSG02Y","CSUSR01Y","SQL:DCLTRTYP","SQL:DCLTRCAT","COCOM01Y","CSSETATY"],"calls_to":[]},{"file_path":"/Users/ianzepp/github/gauntlet/gauntlet-week-3/aws-mainframe-modernization-carddemo/app/app-transaction-type-db2/cbl/COTRTLIC.cbl","file_name":"COTRTLIC.cbl","file_type":"cbl","name":"DFHCOMMAREA","start_line":493.0,"end_line":496.0,"score":0.2506585717201233,"chunk_type":"data_division","preamble":"File: COTRTLIC.cbl\nProgram: COTRTLIC - Business logic - List Transaction Type for updates and deletes\nData: DFHCOMMAREA (lines 493-496)","summary":"data_division DFHCOMMAREA in COTRTLIC.cbl. uses COPY refs: SQL:CSDB2RWY, CVCRD01Y, SQL:SQLCA, SQL:DCLTRTYP....","content":" 01  DFHCOMMAREA.\n   05  FILLER                                PIC X(1)\n       OCCURS 1 TO 32767 TIMES DEPENDING ON EIBCALEN.\n","comments":"","copy_references":["SQL:CSDB2RWY","CVCRD01Y","SQL:SQLCA","SQL:DCLTRTYP","COCOM01Y","DFHBMSCA","DFHAID","COTTL01Y","COTRTLI","CSDAT01Y","CSMSG01Y","CSUSR01Y","CVACT02Y","SQL:CSDB2RPY"],"calls_to":[]}]}