{"query":"What message handling does CSMSG01Y provide?","top_k_built":10,"results":[{"file_path":"/Users/ianzepp/github/gauntlet/gauntlet-week-3/aws-mainframe-modernization-carddemo/app/cpy/CSMSG02Y.cpy","file_name":"CSMSG02Y.cpy","file_type":"cpy","name":"CSMSG02Y","start_line":1.0,"end_line":35.0,"score":0.36838439106941223,"chunk_type":"copybook","preamble":"File: CSMSG02Y.cpy\nCopybook: CSMSG02Y (lines 1-35)","summary":"copybook CSMSG02Y in CSMSG02Y.cpy.","content":"000700*****************************************************************\n000800* CABENDD.CPY                                                   *\n000900*---------------------------------------------------------------*\n001000* Work areas for abend routine                                  *\n      ******************************************************************\n      * Copyright Amazon.com, Inc. or its affiliates.                   \n      * All Rights Reserved.                                            \n      *                                                                 \n      * Licensed under the Apache License, Version 2.0 (the \"License\"). \n      * You may not use this file except in compliance with the License.\n      * You may obtain a copy of the License at                         \n      *                                                                 \n      *    http://www.apache.org/licenses/LICENSE-2.0                   \n      *                                                                 \n      * Unless required by applicable law or agreed to in writing,      \n      * software distributed under the License is distributed on an     \n      * \"AS IS\" BASIS, WITHOUT WARRANTIES OR CONDITIONS OF ANY KIND,    \n      * either express or implied. See the License for the specific     \n      * language governing permissions and limitations under the License\n      ****************************************************************** \n001200 01  ABEND-DATA.\n001300   05  ABEND-CODE                            PIC X(4)\n001400       VALUE SPACES.\n001500   05  ABEND-CULPRIT                         PIC X(8)\n001600       VALUE SPACES.\n001700   05  ABEND-REASON                          PIC X(50)\n001800       VALUE SPACES.\n001900   05  ABEND-MSG                             PIC X(72)\n002000       VALUE SPACES.\n\n\n\n      *\n      * Ver: CardDemo_v1.0-15-g27d6c6f-68 Date: 2022-07-19 23:15:58 CDT\n      *\n","comments":"","copy_references":[],"calls_to":[]},{"file_path":"/Users/ianzepp/github/gauntlet/gauntlet-week-3/aws-mainframe-modernization-carddemo/app/cpy/CSMSG01Y.cpy","file_name":"CSMSG01Y.cpy","file_type":"cpy","name":"CSMSG01Y","start_line":1.0,"end_line":24.0,"score":0.35535261034965515,"chunk_type":"copybook","preamble":"File: CSMSG01Y.cpy\nCopybook: CSMSG01Y (lines 1-24)","summary":"copybook CSMSG01Y in CSMSG01Y.cpy. comment hint: Copyright Amazon.com, Inc. or its affiliates..","content":"      ******************************************************************\n      * Copyright Amazon.com, Inc. or its affiliates.                   \n      * All Rights Reserved.                                            \n      *                                                                 \n      * Licensed under the Apache License, Version 2.0 (the \"License\"). \n      * You may not use this file except in compliance with the License.\n      * You may obtain a copy of the License at                         \n      *                                                                 \n      *    http://www.apache.org/licenses/LICENSE-2.0                   \n      *                                                                 \n      * Unless required by applicable law or agreed to in writing,      \n      * software distributed under the License is distributed on an     \n      * \"AS IS\" BASIS, WITHOUT WARRANTIES OR CONDITIONS OF ANY KIND,    \n      * either express or implied. See the License for the specific     \n      * language governing permissions and limitations under the License\n      ****************************************************************** \n       01 CCDA-COMMON-MESSAGES.\n         05 CCDA-MSG-THANK-YOU         PIC X(50) VALUE\n              'Thank you for using CardDemo application...      '.\n         05 CCDA-MSG-INVALID-KEY       PIC X(50) VALUE\n              'Invalid key pressed. Please see below...         '.\n      *\n      * Ver: CardDemo_v1.0-15-g27d6c6f-68 Date: 2022-07-19 23:15:58 CDT\n      *\n","comments":"\nCopyright Amazon.com, Inc. or its affiliates.\nAll Rights Reserved.\n\nLicensed under the Apache License, Version 2.0 (the \"License\").\nYou may not use this file except in compliance with the License.\nYou may obtain a copy of the License at\n\nhttp://www.apache.org/licenses/LICENSE-2.0\n\nUnless required by applicable law or agreed to in writing,\nsoftware distributed under the License is distributed on an\n\"AS IS\" BASIS, WITHOUT WARRANTIES OR CONDITIONS OF ANY KIND,\neither express or implied. See the License for the specific\nlanguage governing permissions and limitations under the License\n","copy_references":[],"calls_to":[]},{"file_path":"/Users/ianzepp/github/gauntlet/gauntlet-week-3/aws-mainframe-modernization-carddemo/app/app-transaction-type-db2/cbl/COTRTLIC.cbl","file_name":"COTRTLIC.cbl","file_type":"cbl","name":"WS-MISC-STORAGE","start_line":84.0,"end_line":376.0,"score":0.3184056282043457,"chunk_type":"data_division","preamble":"File: COTRTLIC.cbl\nProgram: COTRTLIC - Business logic - List Transaction Type for updates and deletes\nData: WS-MISC-STORAGE (lines 84-376)","summary":"data_division WS-MISC-STORAGE in COTRTLIC.cbl. uses COPY refs: SQL:CSDB2RWY, CVCRD01Y, SQL:SQLCA, SQL:DCLTRTYP....","content":" 01  WS-MISC-STORAGE.\n******************************************************************\n* General CICS related\n******************************************************************\n\n   05 WS-CICS-PROCESSNG-VARS.\n      07 WS-RESP-CD            PIC S9(9) COMP VALUE ZEROS.\n      07 WS-REAS-CD            PIC S9(9) COMP VALUE ZEROS.\n      07 WS-TRANID             PIC X(4)       VALUE SPACES.\n\n\n******************************************************************\n* Input edits\n******************************************************************\n   05 WS-INPUT-FLAG                          PIC X(1).\n     88  INPUT-OK                            VALUES '0'\n                                                    ' '\n                                             LOW-VALUES.\n     88  INPUT-ERROR                         VALUE '1'.\n   05  WS-EDIT-TYPE-FLAG                     PIC X(1).\n     88  FLG-TYPEFILTER-NOT-OK               VALUE '0'.\n     88  FLG-TYPEFILTER-ISVALID              VALUE '1'.\n     88  FLG-TYPEFILTER-BLANK                VALUE ' '.\n   05  WS-EDIT-DESC-FLAG                     PIC X(1).\n     88  FLG-DESCFILTER-NOT-OK               VALUE '0'.\n     88  FLG-DESCFILTER-ISVALID              VALUE '1'.\n     88  FLG-DESCFILTER-BLANK                VALUE ' '.\n   05 WS-TYPEFILTER-CHANGED                  PIC X(1).\n     88  FLG-TYPEFILTER-CHANGED-NO           VALUE LOW-VALUES.\n     88  FLG-TYPEFILTER-CHANGED-YES          VALUE 'Y'.\n   05 WS-DESCFILTER-CHANGED                  PIC X(1).\n     88  FLG-DESCFILTER-CHANGED-NO           VALUE LOW-VALUES.\n     88  FLG-DESCFILTER-CHANGED-YES          VALUE 'Y'.\n   05 WS-ROW-RECORDS-CHANGED                 PIC X(01)\n                                             OCCURS 7 TIMES.\n     88  FLG-ROW-DESCR-CHANGED-NO            VALUE LOW-VALUES.\n     88  FLG-ROW-DESCR-CHANGED-YES           VALUE 'Y'.\n   05 WS-DELETE-STATUS                       PIC X(1).\n     88  FLG-DELETED-NO                      VALUE LOW-VALUES.\n     88  FLG-DELETED-YES                     VALUE 'Y'.\n   05 WS-UPDATE-STATUS                       PIC X(1).\n     88  FLG-UPDATED-NO                      VALUE LOW-VALUES.\n     88  FLG-UPDATE-COMPLETED                     VALUE 'Y'.\n   05 WS-ROW-SELECTION-CHANGED               PIC X(1).\n     88  FLG-ROW-SELECTION-CHANGED-NO        VALUE LOW-VALUES.\n     88  FLG-ROW-SELECTION-CHANGED-YES       VALUE 'Y'.\n   05 WS-BAD-SELECTION-ACTION                PIC X(1).\n     88  FLG-BAD-ACTIONS-SELECTED-NO         VALUE LOW-VALUES.\n     88  FLG-BAD-ACTIONS-SELECTED-YES        VALUE 'Y'.\n   05 WS-ARRAY-DESCRIPTION-FLGS              PIC X(1).\n     88  FLG-ROW-DESCRIPTION-ISVALID         VALUE LOW-VALUES\n                                                   SPACES.\n     88  FLG-ROW-DESCRIPTION-NOT-OK          VALUE '0'.\n     88  FLG-ROW-DESCRIPTION-BLANK           VALUE 'B'.\n   05  WS-DATACHANGED-FLAG                   PIC X(1).\n     88  NO-CHANGES-FOUND                    VALUE '0'.\n     88  CHANGES-HAVE-OCCURRED               VALUE '1'.\n\n*  Generic Input Edits\n   05  WS-GENERIC-EDITS.\n     10 WS-EDIT-VARIABLE-NAME                PIC X(25).\n\n     10 WS-EDIT-ALPHANUM-ONLY                PIC X(256).\n     10 WS-EDIT-ALPHANUM-LENGTH              PIC S9(4) COMP-3.\n\n     10 WS-EDIT-ALPHANUM-ONLY-FLAGS          PIC X(1).\n        88  FLG-ALPHNANUM-ISVALID            VALUE LOW-VALUES.\n        88  FLG-ALPHNANUM-NOT-OK             VALUE '0'.\n        88  FLG-ALPHNANUM-BLANK              VALUE 'B'.\n\n   05  WS-OTHER-EDIT-VARS.\n     10 WS-RECORDS-COUNT                     PIC S9(4) COMP-3\n                                             VALUE 0.\n\n******************************************************************\n*  Input edits array variables\n******************************************************************\n******************************************************************\n*  Screen Data Array         52 CHARS X 7 ROWS = 364\n******************************************************************\n\n   05 WS-SCREEN-DATA-IN.\n      10 WS-ALL-ROWS-IN                      PIC X(364).\n      10 FILLER REDEFINES WS-ALL-ROWS-IN.\n         15 WS-SCREEN-ROWS-IN OCCURS  7 TIMES.\n            20 WS-EACH-ROW-IN.\n               25 WS-EACH-TTYP-IN.\n                  30 WS-ROW-TR-CODE-IN       PIC X(02).\n                  30 WS-ROW-TR-DESC-IN       PIC X(50).\n\n\n   05 WS-EDIT-SELECT-COUNTER                 PIC S9(04)\n                                             USAGE COMP-3\n                                             VALUE 0.\n   05 WS-EDIT-SELECT-FLAGS                   PIC X(7)\n                                             VALUE LOW-VALUES.\n   05 FILLER  REDEFINES  WS-EDIT-SELECT-FLAGS.\n      10 WS-EDIT-SELECT                      PIC X(1)\n                                             OCCURS 7 TIMES.\n         88 SELECT-OK                        VALUES 'D', 'U'.\n         88 DELETE-REQUESTED-ON              VALUE 'D'.\n         88 UPDATE-REQUESTED-ON              VALUE 'U'.\n         88 SELECT-BLANK                     VALUES\n                                             ' ',\n                                             LOW-VALUES.\n\n   05 WS-EDIT-SELECT-ERROR-FLAGS             PIC X(7)\n                                             VALUE LOW-VALUES.\n   05 FILLER  REDEFINES WS-EDIT-SELECT-ERROR-FLAGS.\n      10 WS-EDIT-SELECT-ERRORS               OCCURS 7 TIMES.\n         20 WS-ROW-TRTSELECT-ERROR           PIC X(1).\n            88 WS-ROW-SELECT-ERROR           VALUE '1'.\n\n   05 WS-SUBSCRIPT-VARS.\n      10 I                                  PIC S9(4) COMP\n                                            VALUE 0.\n      10 I-SELECTED                         PIC S9(4) COMP\n                                            VALUE 0.\n   05 WS-ACTIONS-SELECTED.\n      07 WS-ACTIONS-REQUESTED               PIC S9(04)\n                                            USAGE COMP-3\n                                            VALUE 0.\n         88 WS-ONLY-1-ACTION                VALUE 1.\n         88 WS-MORETHAN1ACTION              VALUES 2 THRU 7.\n      07 WS-DELETES-REQUESTED               PIC S9(04)\n                                            USAGE COMP-3\n                                            VALUE 0.\n      07 WS-UPDATES-REQUESTED               PIC S9(04)\n                                            USAGE COMP-3\n                                            VALUE 0.\n      07 WS-NO-ACTIONS-SELECTED             PIC S9(04)\n                                            COMP-3\n                                            VALUE 0.\n   05 WS-VALID-ACTIONS-SELECTED             PIC S9(04)\n                                            USAGE COMP-3\n                                            VALUE 0.\n      88 WS-ONLY-1-VALID-ACTION             VALUE 1.\n\n******************************************************************\n* Output edits\n******************************************************************\n   05 CICS-OUTPUT-EDIT-VARS.\n     10  TRAN-TYPE-CD-X                      PIC X(02).\n     10  TRAN-TYPE-CD-N REDEFINES TRAN-TYPE-CD-X\n                                             PIC 9(02).\n     10  FLG-PROTECT-SELECT-ROWS             PIC X(1).\n     88  FLG-PROTECT-SELECT-ROWS-NO          VALUE '0'.\n     88  FLG-PROTECT-SELECT-ROWS-YES         VALUE '1'.\n******************************************************************\n* Output Message Construction\n******************************************************************\n   05  WS-LONG-MSG                           PIC X(800).\n   05  WS-INFO-MSG                           PIC X(45).\n     88  WS-NO-INFO-MESSAGE                  VALUES\n                                             SPACES LOW-VALUES.\n     88  WS-INFORM-REC-ACTIONS               VALUE\n         'Type U to update, D to delete any record'.\n     88  WS-INFORM-DELETE                    VALUE\n         'Delete HIGHLIGHTED row ? Press F10 to confirm'.\n     88  WS-INFORM-UPDATE                    VALUE\n         'Update HIGHLIGHTED row. Press F10 to save'.\n     88  WS-INFORM-DELETE-SUCCESS            VALUE\n         'HIGHLIGHTED row deleted.Hit Enter to continue'.\n     88  WS-INFORM-UPDATE-SUCCESS            VALUE\n         'HIGHLIGHTED row was updated'.\n   05  WS-RETURN-MSG                         PIC X(75).\n     88  WS-RETURN-MSG-OFF                   VALUE SPACES.\n     88  WS-EXIT-MESSAGE                     VALUE\n         'PF03 pressed. Exiting'.\n     88  WS-MESG-NO-RECORDS-FOUND            VALUE\n         'No records found for this search condition.'.\n     88  WS-MESG-NO-MORE-RECORDS             VALUE\n         'No more pages for these search conditions'.\n     88  WS-MESG-MORE-THAN-1-ACTION          VALUE\n         'Please select only 1 action'.\n     88  WS-MESG-INVALID-ACTION-CODE         VALUE\n         'Action code selected is invalid'.\n     88  WS-MESG-NO-CHANGES-DETECTED         VALUE\n         'No change detected with respect to database values.'.\n   05  WS-PFK-FLAG                           PIC X(1).\n     88  PFK-VALID                           VALUE '0'.\n     88  PFK-INVALID                         VALUE '1'.\n   05 WS-STRING-FORMAT-VARS.\n      10 WS-STRING-MID                      PIC 9(3) VALUE 0.\n      10 WS-STRING-LEN                      PIC 9(3) VALUE 0.\n      10 WS-STRING-OUT                      PIC X(45).\n\n******************************************************************\n* Data Handling\n******************************************************************\n   05 WS-DATA-FILTERS.\n      10  WS-START-KEY                      PIC X(02).\n      10  WS-TYPE-CD-FILTER                 PIC X(02)\n                                            VALUE SPACES.\n      10  WS-TYPE-DESC-FILTER               PIC X(52).\n      10  WS-TYPE-CD-DELETE-FILTER.\n          15 FILLER                         PIC X(01)\n                                            VALUE '('.\n          15 WS-TYPE-CD-DELETE-FILTER-X.\n             20 WS-TYPE-CD-DELETE-KEYS      OCCURS 7 TIMES.\n                25 FILLER                   PIC X(01)\n                                            VALUE QUOTE.\n                25 WS-TYPE-CD-DELETE-KEY    PIC","comments":"","copy_references":["SQL:CSDB2RWY","CVCRD01Y","SQL:SQLCA","SQL:DCLTRTYP","COCOM01Y","DFHBMSCA","DFHAID","COTTL01Y","COTRTLI","CSDAT01Y","CSMSG01Y","CSUSR01Y","CVACT02Y","SQL:CSDB2RPY"],"calls_to":[]},{"file_path":"/Users/ianzepp/github/gauntlet/gauntlet-week-3/aws-mainframe-modernization-carddemo/app/app-vsam-mq/cbl/CODATE01.cbl","file_name":"CODATE01.cbl","file_type":"cbl","name":"DATA DIVISION","start_line":9.0,"end_line":124.0,"score":0.3062855005264282,"chunk_type":"data_division","preamble":"File: CODATE01.cbl\nProgram: CODATE01\nSection: DATA DIVISION (lines 9-124)","summary":"data_division DATA DIVISION in CODATE01.cbl. uses COPY refs: CMQGMOV, CMQPMOV, CMQMDV, CMQODV....","content":" DATA DIVISION.                                                   00090012\n                                                                  00100012\n WORKING-STORAGE SECTION.                                         00110012\n                                                                  00120012\n 01 WS-MQ-MSG-FLAG                PIC X(01) VALUE 'N'.            00130012\n    88  NO-MORE-MSGS              VALUE 'Y'.                      00140012\n                                                                  00150012\n 01 WS-RESP-QUEUE-STS            PIC X(01) VALUE 'N'.             00160012\n    88  RESP-QUEUE-OPEN          VALUE 'Y'.                       00170012\n                                                                  00180012\n 01 WS-ERR-QUEUE-STS             PIC X(01) VALUE 'N'.             00190012\n    88  ERR-QUEUE-OPEN          VALUE 'Y'.                        00200012\n                                                                  00210012\n 01 WS-REPLY-QUEUE-STS           PIC X(01) VALUE 'N'.             00220012\n    88  REPLY-QUEUE-OPEN         VALUE 'Y'.                       00230012\n                                                                  00240012\n                                                                  00250012\n 01 WS-CICS-RESP-CDS.                                             00260012\n    05  WS-CICS-RESP1-CD        PIC S9(08) COMP VALUE ZERO.       00270012\n    05  WS-CICS-RESP2-CD        PIC S9(08) COMP VALUE ZERO.       00280012\n    05  WS-CICS-RESP1-CD-D      PIC 9(08) VALUE ZERO.             00290012\n    05  WS-CICS-RESP2-CD-D      PIC 9(08) VALUE ZERO.             00300012\n                                                                  00310012\n***********************************************                   00320012\n**             DATE FIELDS                   **                   00330012\n***********************************************                   00340012\n 01 WS-DATE-TIME.                                                 00350012\n    10 WS-ABS-TIME                  PIC S9(15) COMP-3 VALUE ZERO. 00360012\n    10 WS-MMDDYYYY                  PIC X(10) VALUE SPACES.       00370012\n    10 WS-TIME                      PIC X(8)  VALUE SPACES.       00380012\n***********************************************                   00390012\n**             MQ FIELDS                     **                   00400012\n***********************************************                   00410012\n 01 MQ-QUEUE                        PIC X(48).                    00420012\n 01 MQ-QUEUE-REPLY                  PIC X(48).                    00430012\n 01 MQ-HCONN                        PIC S9(09) BINARY VALUE 0.    00440012\n 01 MQ-CONDITION-CODE               PIC S9(09) BINARY VALUE 0.    00450012\n 01 MQ-REASON-CODE                  PIC S9(09) BINARY VALUE 0.    00460012\n 01 MQ-HOBJ                         PIC S9(09) BINARY VALUE 0.    00470012\n 01 MQ-OPTIONS                      PIC S9(09) BINARY VALUE 0.    00480012\n 01 MQ-BUFFER-LENGTH                PIC S9(09) BINARY.            00490012\n 01 MQ-BUFFER                       PIC X(1000).                  00500012\n 01 MQ-DATA-LENGTH                  PIC S9(09) BINARY.            00510012\n 01 MQ-CORRELID                     PIC X(24).                    00520012\n 01 MQ-MSG-ID                       PIC X(24).                    00530012\n 01 MQ-MSG-COUNT                    PIC 9(09).                    00540012\n 01 SAVE-CORELID                    PIC X(24).                    00550012\n 01 SAVE-MSGID                      PIC X(24).                    00560012\n 01 SAVE-REPLY2Q                    PIC X(48).                    00570012\n 01 MQ-ERR-DISPLAY.                                               00580012\n     05 MQ-ERROR-PARA                   PIC X(25) .               00590012\n     05 FILLER                          PIC X(02) VALUE SPACES.   00600012\n     05 MQ-APPL-RETURN-MESSAGE          PIC X(25).                00610012\n     05 FILLER                          PIC X(02) VALUE SPACES.   00620012\n     05 MQ-APPL-CONDITION-CODE          PIC 9(02).                00630012\n     05 FILLER                          PIC X(02) VALUE SPACES.   00640012\n     05 MQ-APPL-REASON-CODE             PIC 9(05).                00650012\n     05 FILLER                          PIC X(02) VALUE SPACES.   00660012\n     05 MQ-APPL-QUEUE-NAME              PIC X(48).                00670012\n                                                                  00680012\n                                                                  00690012\n 01 MQ-GET-MESSAGE-OPTIONS.                                       00700012\n COPY CMQGMOV.                                                    00710012\n                                                                  00720012\n                                                                  00730012\n 01 MQ-PUT-MESSAGE-OPTIONS.                                       00740012\n COPY CMQPMOV.                                                    00750012\n                                                                  00760012\n                                                                  00770012\n 01 MQ-MESSAGE-DESCRIPTOR.                                        00780012\n COPY CMQMDV.                                                     00790012\n                                                                  00800012\n                                                                  00810012\n 01 MQ-OBJECT-DESCRIPTOR.                                         00820012\n COPY CMQODV.                                                     00830012\n                                                                  00840012\n                                                                  00850012\n 01 MQ-CONSTANTS.                                                 00860012\n COPY CMQV.                                                       00870012\n                                                                  00880012\n 01 MQ-GET-QUEUE-MESSAGE.                                         00890012\n COPY CMQTML.                                                     00900012\n                                                                  00910012\n 01  QUEUE-INFO.                                                  00920012\n     05 QMGR-NAME                   PIC X(48) VALUE SPACES.       00930012\n     05 INPUT-QUEUE-NAME            PIC X(48) VALUE SPACES.       00940012\n     05 REPLY-QUEUE-NAME            PIC X(48) VALUE SPACES.       00950012\n     05 ERROR-QUEUE-NAME            PIC X(48) VALUE SPACES.       00960012\n                                                                  00970012\n 01 INPUT-QUEUE-HANDLE              PIC S9(09) BINARY VALUE 0.    00980012\n                                                                  00990012\n 01 OUTPUT-QUEUE-HANDLE             PIC S9(09) BINARY VALUE 0.    01000012\n                                                                  01010012\n 01 ERROR-QUEUE-HANDLE              PIC S9(09) BINARY VALUE 0.    01020012\n                                                                  01030012\n 01 QMGR-HANDLE-CONN                PIC S9(09) BINARY VALUE 0.    01040012\n 01 QUEUE-MESSAGE                   PIC X(1000).                  01050012\n 01 REQUEST-MESSAGE                 PIC X(1000).                  01060012\n 01 REPLY-MESSAGE                   PIC X(1000).                  01070012\n 01 ERROR-MESSAGE                   PIC X(1000).                  01080012\n 01 REQUEST-MSG-COPY.                                             01090012\n    10 WS-FUNC                      PIC X(04) VALUE SPACES.       01100012\n    10 WS-KEY                       PIC 9(11) VALUE ZEROES.       01110012\n    10 WS-FILLER                    PIC X(985) VALUE SPACES.      01120012\n                                                                  01130012\n       01 WS-VARIABLES.                                                 01140012\n          05 LIT-ACCTFILENAME                      PIC X(8)             01150012\n                                                   VALUE 'ACCTDAT '.    01160012\n          05 WS-RESP-CD                          PIC S9(09) COMP        01170012\n                                                   VALUE ZEROS.         01180012\n          05 WS-REAS-CD                          PIC S9(09) COMP        01190012\n                                                   VALUE ZEROS.         01200012\n                                                                        01210012\n                                                                  01220012\n LINKAGE SECTION.                                                 01230012\n                                                                  01240012","comments":"","copy_references":["CMQGMOV","CMQPMOV","CMQMDV","CMQODV","CMQV","CMQTML","REPLACING","03220012"],"calls_to":[]},{"file_path":"/Users/ianzepp/github/gauntlet/gauntlet-week-3/aws-mainframe-modernization-carddemo/app/app-vsam-mq/cbl/COACCT01.cbl","file_name":"COACCT01.cbl","file_type":"cbl","name":"DATA DIVISION","start_line":9.0,"end_line":175.0,"score":0.301570862531662,"chunk_type":"data_division","preamble":"File: COACCT01.cbl\nProgram: COACCT01\nSection: DATA DIVISION (lines 9-175)","summary":"data_division DATA DIVISION in COACCT01.cbl. uses COPY refs: CMQGMOV, CMQPMOV, CMQMDV, CMQODV....","content":" DATA DIVISION.                                                   00090000\n                                                                  00100000\n WORKING-STORAGE SECTION.                                         00110000\n                                                                  00170000\n 01 WS-MQ-MSG-FLAG                PIC X(01) VALUE 'N'.            00180007\n    88  NO-MORE-MSGS              VALUE 'Y'.                      00190007\n                                                                  00200000\n 01 WS-RESP-QUEUE-STS            PIC X(01) VALUE 'N'.             00210007\n    88  RESP-QUEUE-OPEN          VALUE 'Y'.                       00220007\n                                                                  00230000\n 01 WS-ERR-QUEUE-STS             PIC X(01) VALUE 'N'.             00240007\n    88  ERR-QUEUE-OPEN          VALUE 'Y'.                        00250007\n                                                                  00260000\n 01 WS-REPLY-QUEUE-STS           PIC X(01) VALUE 'N'.             00270007\n    88  REPLY-QUEUE-OPEN         VALUE 'Y'.                       00280007\n                                                                  00290000\n                                                                  00370000\n 01 WS-CICS-RESP-CDS.                                             00380007\n    05  WS-CICS-RESP1-CD        PIC S9(08) COMP VALUE ZERO.       00390007\n    05  WS-CICS-RESP2-CD        PIC S9(08) COMP VALUE ZERO.       00400007\n    05  WS-CICS-RESP1-CD-D      PIC 9(08) VALUE ZERO.             00430007\n    05  WS-CICS-RESP2-CD-D      PIC 9(08) VALUE ZERO.             00440007\n                                                                  00450000\n***********************************************                   00460000\n**             DATE FIELDS                   **                   00470000\n***********************************************                   00480000\n 01 WS-DATE-TIME.                                                 00490000\n    10 WS-ABS-TIME                  PIC S9(15) COMP-3 VALUE ZERO. 00500000\n    10 WS-MMDDYYYY                  PIC X(10) VALUE SPACES.       00510000\n    10 WS-TIME                      PIC X(8)  VALUE SPACES.       00520000\n***********************************************                   00530000\n**             MQ FIELDS                     **                   00540000\n***********************************************                   00550000\n 01 MQ-QUEUE                        PIC X(48).                    00570000\n 01 MQ-QUEUE-REPLY                  PIC X(48).                    00580000\n 01 MQ-HCONN                        PIC S9(09) BINARY VALUE 0.    00590000\n 01 MQ-CONDITION-CODE               PIC S9(09) BINARY VALUE 0.    00600000\n 01 MQ-REASON-CODE                  PIC S9(09) BINARY VALUE 0.    00610000\n 01 MQ-HOBJ                         PIC S9(09) BINARY VALUE 0.    00620000\n 01 MQ-OPTIONS                      PIC S9(09) BINARY VALUE 0.    00630000\n 01 MQ-BUFFER-LENGTH                PIC S9(09) BINARY.            00640000\n 01 MQ-BUFFER                       PIC X(1000).                  00650000\n 01 MQ-DATA-LENGTH                  PIC S9(09) BINARY.            00660000\n 01 MQ-CORRELID                     PIC X(24).                    00670000\n 01 MQ-MSG-ID                       PIC X(24).                    00680000\n 01 MQ-MSG-COUNT                    PIC 9(09).                    00690000\n 01 SAVE-CORELID                    PIC X(24).                    00700000\n 01 SAVE-MSGID                      PIC X(24).                    00710000\n 01 SAVE-REPLY2Q                    PIC X(48).                    00720000\n 01 MQ-ERR-DISPLAY.                                               00730000\n     05 MQ-ERROR-PARA                   PIC X(25) .               00740000\n     05 FILLER                          PIC X(02) VALUE SPACES.   00750000\n     05 MQ-APPL-RETURN-MESSAGE          PIC X(25).                00760000\n     05 FILLER                          PIC X(02) VALUE SPACES.   00770000\n     05 MQ-APPL-CONDITION-CODE          PIC 9(02).                00780000\n     05 FILLER                          PIC X(02) VALUE SPACES.   00790000\n     05 MQ-APPL-REASON-CODE             PIC 9(05).                00800000\n     05 FILLER                          PIC X(02) VALUE SPACES.   00810000\n     05 MQ-APPL-QUEUE-NAME              PIC X(48).                00820000\n                                                                  00830000\n                                                                  00840000\n 01 MQ-GET-MESSAGE-OPTIONS.                                       00850000\n COPY CMQGMOV.                                                    00860000\n                                                                  00870000\n                                                                  00880000\n 01 MQ-PUT-MESSAGE-OPTIONS.                                       00890000\n COPY CMQPMOV.                                                    00900000\n                                                                  00910000\n                                                                  00920000\n 01 MQ-MESSAGE-DESCRIPTOR.                                        00930000\n COPY CMQMDV.                                                     00940000\n                                                                  00950000\n                                                                  00960000\n 01 MQ-OBJECT-DESCRIPTOR.                                         00970000\n COPY CMQODV.                                                     00980000\n                                                                  00990000\n                                                                  01000000\n 01 MQ-CONSTANTS.                                                 01010000\n COPY CMQV.                                                       01020000\n                                                                  01030000\n 01 MQ-GET-QUEUE-MESSAGE.                                         01040000\n COPY CMQTML.                                                     01050000\n                                                                  01060000\n 01  QUEUE-INFO.                                                  01070000\n     05 QMGR-NAME                   PIC X(48) VALUE SPACES.       01080007\n     05 INPUT-QUEUE-NAME            PIC X(48) VALUE SPACES.       01090000\n     05 REPLY-QUEUE-NAME            PIC X(48) VALUE SPACES.       01100000\n     05 ERROR-QUEUE-NAME            PIC X(48) VALUE SPACES.       01110000\n                                                                  01120000\n 01 INPUT-QUEUE-HANDLE              PIC S9(09) BINARY VALUE 0.    01130000\n                                                                  01140000\n 01 OUTPUT-QUEUE-HANDLE             PIC S9(09) BINARY VALUE 0.    01150000\n                                                                  01160000\n 01 ERROR-QUEUE-HANDLE              PIC S9(09) BINARY VALUE 0.    01170000\n                                                                  01180000\n 01 QMGR-HANDLE-CONN                PIC S9(09) BINARY VALUE 0.    01190000\n 01 QUEUE-MESSAGE                   PIC X(1000).                  01200000\n 01 REQUEST-MESSAGE                 PIC X(1000).                  01210000\n 01 REPLY-MESSAGE                   PIC X(1000).                  01220000\n 01 ERROR-MESSAGE                   PIC X(1000).                  01230000\n 01 REQUEST-MSG-COPY.                                             01240002\n    10 WS-FUNC                      PIC X(04) VALUE SPACES.       01241000\n    10 WS-KEY                       PIC 9(11) VALUE ZEROES.       01242000\n    10 WS-FILLER                    PIC X(985) VALUE SPACES.      01243000\n                                                                  01250000\n       01 WS-VARIABLES.                                                 01251000\n          05 LIT-ACCTFILENAME                      PIC X(8)             01251100\n                                                   VALUE 'ACCTDAT '.    01251200\n          05 WS-RESP-CD                          PIC S9(09) COMP        01251300\n                                                   VALUE ZEROS.         01251400\n          05 WS-REAS-CD                          PIC S9(09) COMP        01251500\n                                                   VALUE ZEROS.         01251600\n         05  WS-XREF-RID.                                               01251700\n           10  WS-CARD-RID-CARDNUM                 PIC X(16).           01252000\n           10  WS-CARD-RID-CUST-ID                 PIC 9(09).           01253000\n           10  WS-CARD-RID-CUST-ID-X REDEFINES                          01254000\n                  WS-CARD-RID-CUST-ID              PIC X(09).           01255000\n           10  WS-CARD-RID-ACCT-ID                 PIC 9(11).           01256000\n           10  WS-CARD-RID-ACCT-ID-X REDEFINES                          01257000\n                  WS-CARD-RID-ACCT-ID              PIC X(11).           01258000\n                                                                        01259000\n       01 WS-ACCT-RESPONSE.                                             01259107\n                                                                        01259207\n           05  WS-ACCT-LBL                       PIC X(13) VALUE        01259307\n                                                     'ACCOUNT ID : '.   01259407\n           05  WS-ACCT-ID                        PIC 9(11) VALUE ZEROES.01259507\n           05  WS-STATUS-LBL                     PIC X(17) VALUE        01259608\n                                                'ACCOUNT STATUS : '.    01259707\n           05  WS-ACCT-ACTIVE-STATUS             PIC X(01) VALUE SPACES.01259807\n           05  WS-CURR-BAL-LBL                   PIC X(10) VALUE        01259907\n                                                     'BALANCE : '.      01260007\n           05  WS-A","comments":"","copy_references":["CMQGMOV","CMQPMOV","CMQMDV","CMQODV","CMQV","CMQTML","CVACT01Y","REPLACING","03500000"],"calls_to":[]},{"file_path":"/Users/ianzepp/github/gauntlet/gauntlet-week-3/aws-mainframe-modernization-carddemo/app/cbl/COSGN00C.cbl","file_name":"COSGN00C.cbl","file_type":"cbl","name":"MAIN-PARA","start_line":73.0,"end_line":107.0,"score":0.2886163294315338,"chunk_type":"paragraph","preamble":"File: COSGN00C.cbl\nProgram: COSGN00C - CICS COBOL Program - Signon Screen for the CardDemo Application\nParagraph: MAIN-PARA (lines 73-107)\nReferences: COPY COCOM01Y, COPY COSGN00, COPY COTTL01Y, COPY CSDAT01Y, COPY CSMSG01Y, COPY CSUSR01Y, COPY DFHAID, COPY DFHBMSCA\nCalls: PERFORM PROCESS-ENTER-KEY, PERFORM SEND-PLAIN-TEXT, PERFORM SEND-SIGNON-SCREEN","summary":"paragraph MAIN-PARA in COSGN00C.cbl. uses COPY refs: COCOM01Y, COSGN00, COTTL01Y, CSDAT01Y.... invokes: PERFORM PROCESS-ENTER-KEY, PERFORM SEND-PLAIN-TEXT, PERFORM SEND-SIGNON-SCREEN.","content":"       MAIN-PARA.\n\n           SET ERR-FLG-OFF TO TRUE\n\n           MOVE SPACES TO WS-MESSAGE\n                          ERRMSGO OF COSGN0AO\n\n           IF EIBCALEN = 0\n               MOVE LOW-VALUES TO COSGN0AO\n               MOVE -1       TO USERIDL OF COSGN0AI\n               PERFORM SEND-SIGNON-SCREEN\n           ELSE\n               EVALUATE EIBAID\n                   WHEN DFHENTER\n                       PERFORM PROCESS-ENTER-KEY\n                   WHEN DFHPF3\n                       MOVE CCDA-MSG-THANK-YOU        TO WS-MESSAGE\n                       PERFORM SEND-PLAIN-TEXT\n                   WHEN OTHER\n                       MOVE 'Y'                       TO WS-ERR-FLG\n                       MOVE CCDA-MSG-INVALID-KEY      TO WS-MESSAGE\n                       PERFORM SEND-SIGNON-SCREEN\n               END-EVALUATE\n           END-IF.\n\n           EXEC CICS RETURN\n                     TRANSID (WS-TRANID)\n                     COMMAREA (CARDDEMO-COMMAREA)\n                     LENGTH(LENGTH OF CARDDEMO-COMMAREA)\n           END-EXEC.\n\n\n      *----------------------------------------------------------------*\n      *                      PROCESS-ENTER-KEY\n      *----------------------------------------------------------------*","comments":"","copy_references":["COCOM01Y","COSGN00","COTTL01Y","CSDAT01Y","CSMSG01Y","CSUSR01Y","DFHAID","DFHBMSCA"],"calls_to":["PERFORM PROCESS-ENTER-KEY","PERFORM SEND-PLAIN-TEXT","PERFORM SEND-SIGNON-SCREEN"]},{"file_path":"/Users/ianzepp/github/gauntlet/gauntlet-week-3/aws-mainframe-modernization-carddemo/app/app-transaction-type-db2/cbl/COTRTUPC.cbl","file_name":"COTRTUPC.cbl","file_type":"cbl","name":"WS-MISC-STORAGE","start_line":35.0,"end_line":199.0,"score":0.28774499893188477,"chunk_type":"data_division","preamble":"File: COTRTUPC.cbl\nProgram: 00220000 - Business logic                                    *00030000 - Accept and process TRANSACTION TYPE UPDATE        *00040000\nData: WS-MISC-STORAGE (lines 35-199)","summary":"data_division WS-MISC-STORAGE in COTRTUPC.cbl. uses COPY refs: CVCRD01Y, DFHBMSCA, DFHAID, COTTL01Y....","content":" 01  WS-MISC-STORAGE.                                             00350000\n******************************************************************00360000\n* General CICS related                                            00370000\n******************************************************************00380000\n   05 WS-CICS-PROCESSNG-VARS.                                     00390000\n      07 WS-RESP-CD                          PIC S9(09) COMP      00400000\n                                             VALUE ZEROS.         00410000\n      07 WS-REAS-CD                          PIC S9(09) COMP      00420000\n                                             VALUE ZEROS.         00430000\n      07 WS-TRANID                           PIC X(4)             00440000\n                                             VALUE SPACES.        00450000\n      07 WS-UCTRANS                          PIC X(4)             00460000\n                                             VALUE SPACES.        00470000\n******************************************************************00480000\n*      Input edits                                                00490000\n******************************************************************00500000\n*  Generic Input Edits                                            00510000\n   05  WS-GENERIC-EDITS.                                          00520000\n     10 WS-EDIT-VARIABLE-NAME                PIC X(25).           00530000\n                                                                  00540000\n     10 WS-EDIT-ALPHANUM-ONLY                PIC X(256).          00550000\n     10 WS-EDIT-ALPHANUM-LENGTH              PIC S9(4) COMP-3.    00560000\n                                                                  00570000\n     10 WS-EDIT-ALPHANUM-ONLY-FLAGS          PIC X(1).            00580000\n        88  FLG-ALPHNANUM-ISVALID            VALUE LOW-VALUES.    00590000\n        88  FLG-ALPHNANUM-NOT-OK             VALUE '0'.           00600000\n        88  FLG-ALPHNANUM-BLANK              VALUE 'B'.           00610000\n                                                                  00620000\n                                                                  00630000\n******************************************************************00640000\n*    Work variables                                               00650000\n******************************************************************00660000\n    05 WS-MISC-VARS.                                              00670000\n      10 WS-DISP-SQLCODE                    PIC ----9.            00680000\n      10 WS-STRING-MID                      PIC 9(3) VALUE 0.     00690000\n      10 WS-STRING-LEN                      PIC 9(3) VALUE 0.     00700000\n      10 WS-STRING-OUT                      PIC X(40).            00710000\n                                                                  00720000\n******************************************************************00730000\n*    Generic date edit variables CCYYMMDD                         00740000\n******************************************************************00750000\n     COPY 'CSUTLDWY'.                                             00760000\n******************************************************************00770000\n   05  WS-DATACHANGED-FLAG                   PIC X(1).            00780000\n     88  NO-CHANGES-FOUND                    VALUE '0'.           00790000\n     88  CHANGE-HAS-OCCURRED                 VALUE '1'.           00800000\n   05  WS-INPUT-FLAG                         PIC X(1).            00810000\n     88  INPUT-OK                            VALUE '0'.           00820000\n     88  INPUT-ERROR                         VALUE '1'.           00830000\n     88  INPUT-PENDING                       VALUE LOW-VALUES.    00840000\n   05  WS-RETURN-FLAG                        PIC X(1).            00850000\n     88  WS-RETURN-FLAG-OFF                  VALUE LOW-VALUES.    00860000\n     88  WS-RETURN-FLAG-ON                   VALUE '1'.           00870000\n   05  WS-PFK-FLAG                           PIC X(1).            00880000\n     88  PFK-VALID                           VALUE '0'.           00890000\n     88  PFK-INVALID                         VALUE '1'.           00900000\n                                                                  00910000\n*  Program specific edits                                         00920000\n*                                                                 00930000\n   05  WS-EDIT-TTYP-FLAG                     PIC X(1).            00940000\n     88  FLG-TRANFILTER-ISVALID              VALUE LOW-VALUES.    00950000\n     88  FLG-TRANFILTER-NOT-OK               VALUE '0'.           00960000\n     88  FLG-TRANFILTER-BLANK                VALUE 'B'.           00970000\n                                                                  00980000\n   05 WS-NON-KEY-FLAGS.                                           00990000\n     10  WS-EDIT-DESC-FLAGS                  PIC X(1).            01000000\n         88  FLG-DESCRIPTION-ISVALID          VALUE LOW-VALUES.   01010000\n         88  FLG-DESCRIPTION-NOT-OK           VALUE '0'.          01020000\n         88  FLG-DESCRIPTION-BLANK            VALUE 'B'.          01030000\n******************************************************************01040000\n* Output edits                                                    01050000\n******************************************************************01060000\n   05 CICS-OUTPUT-EDIT-VARS.                                      01070000\n     10  WS-EDIT-DATE-X                      PIC X(10).           01080000\n     10  FILLER REDEFINES WS-EDIT-DATE-X.                         01090000\n         20 WS-EDIT-DATE-X-YEAR              PIC X(4).            01100000\n         20 FILLER                           PIC X(1).            01110000\n         20 WS-EDIT-DATE-MONTH               PIC X(2).            01120000\n         20 FILLER                           PIC X(1).            01130000\n         20 WS-EDIT-DATE-DAY                 PIC X(2).            01140000\n     10  WS-EDIT-DATE-X REDEFINES                                 01150000\n         WS-EDIT-DATE-X                      PIC 9(10).           01160000\n     10  WS-EDIT-CURRENCY-9-2                PIC X(15).           01170000\n     10  WS-EDIT-CURRENCY-9-2-F              PIC +ZZZ,ZZZ,ZZZ.99. 01180000\n     10  WS-EDIT-NUMERIC-2                   PIC 9(02).           01190000\n     10  WS-EDIT-ALPHANUMERIC-2              PIC X(02).           01200000\n                                                                  01210000\n******************************************************************01220000\n*      File and data Handling                                     01230000\n******************************************************************01240000\n   05  WS-TABLE-READ-FLAGS.                                       01250000\n     10 WS-TRANTYPE-MASTER-READ-FLAG         PIC X(1).            01260000\n        88 FOUND-TRANTYPE-IN-TABLE          VALUE '1'.            01270000\n*  Alpha variables for editing numerics                           01280000\n*                                                                 01290000\n    05 TTYP-UPDATE-RECORD.                                        01300000\n***************************************************************** 01310000\n*    Data-structure for  TRANSACTION TYPE (RECLN 60)              01320000\n***************************************************************** 01330000\n         15  TTUP-UPDATE-TTYP-TYPE               PIC X(02).       01340000\n         15  TTUP-UPDATE-TTYP-TYPE-DESC          PIC X(50).       01350000\n         15  FILLER                              PIC X(08).       01360000\n                                                                  01370000\n                                                                  01380000\n******************************************************************01390000\n*      Output Message Construction                                01400000\n******************************************************************01410000\n   05  WS-INFO-MSG                           PIC X(40).           01420000\n     88  WS-NO-INFO-MESSAGE                 VALUES                01430000\n                                            SPACES LOW-VALUES.    01440000\n     88  FOUND-TRANTYPE-DATA                 VALUE                01450000\n         'Selected transaction type shown above'.                 01460000\n     88  PROMPT-FOR-SEARCH-KEYS              VALUE                01470000\n         'Enter transaction type to be maintained'.               01480000\n     88  PROMPT-CREATE-NEW-RECORD            VALUE                01490000\n         'Press F05 to add. F12 to cancel'.                       01500000\n     88  PROMPT-DELETE-CONFIRM               VALUE                01510000\n         'Delete this record ? Press F4 to confirm'.              01520000\n     88  CONFIRM-DELETE-SUCCESS              VALUE                01530000\n         'Delete successful.'.                                    01540000\n     88  PROMPT-FOR-CHANGES                  VALUE                01550000\n         'Update transaction type details shown.'.                01560000\n     88  PROMPT-FOR-NEWDATA                  VALUE                01570000\n         'Enter new transaction type details.'.                   01580000\n                                                                  01590000\n     88  PROMPT-FOR-CONFIRMATION             VALUE                01600000\n         'Changes validated.Press F5 to save'.                    01610000\n     88  CONFIRM-UPDATE-SUCCESS              VALUE                01620000\n         'Changes committed to database'.                         01630000\n     88  INFORM-FAILURE                      VALUE                01640000\n         'Changes unsuccessful'.                                  01650000\n                                                                  01660000\n   05  WS-RETURN-MSG                         PIC X(75).           01670000\n     88  WS-RETURN-MSG-OF","comments":"","copy_references":["CVCRD01Y","DFHBMSCA","DFHAID","COTTL01Y","COTRTUP","CSDAT01Y","CSMSG01Y","CSMSG02Y","CSUSR01Y","SQL:DCLTRTYP","SQL:DCLTRCAT","COCOM01Y","CSSETATY"],"calls_to":[]},{"file_path":"/Users/ianzepp/github/gauntlet/gauntlet-week-3/aws-mainframe-modernization-carddemo/app/cbl/COCRDSLC.cbl","file_name":"COCRDSLC.cbl","file_type":"cbl","name":"WS-MISC-STORAGE","start_line":36.0,"end_line":161.0,"score":0.2871544361114502,"chunk_type":"data_division","preamble":"File: COCRDSLC.cbl\nProgram: COCRDSLC - Business logic - Accept and process credit card detail request\nData: WS-MISC-STORAGE (lines 36-161)","summary":"data_division WS-MISC-STORAGE in COCRDSLC.cbl. uses COPY refs: CVCRD01Y, COCOM01Y, DFHBMSCA, DFHAID....","content":"       01  WS-MISC-STORAGE.                                                     \n      ******************************************************************        \n      * General CICS related                                                    \n      ******************************************************************        \n         05 WS-CICS-PROCESSNG-VARS.                                             \n            07 WS-RESP-CD                          PIC S9(09) COMP              \n                                                   VALUE ZEROS.                 \n            07 WS-REAS-CD                          PIC S9(09) COMP              \n                                                   VALUE ZEROS.                 \n            07 WS-TRANID                           PIC X(4)                     \n                                                   VALUE SPACES.                \n      ******************************************************************        \n      *      Input edits                                                        \n      ******************************************************************        \n                                                                                \n         05  WS-INPUT-FLAG                         PIC X(1).                    \n           88  INPUT-OK                            VALUE '0'.                   \n           88  INPUT-ERROR                         VALUE '1'.                   \n           88  INPUT-PENDING                       VALUE LOW-VALUES.            \n         05  WS-EDIT-ACCT-FLAG                     PIC X(1).                    \n           88  FLG-ACCTFILTER-NOT-OK               VALUE '0'.                   \n           88  FLG-ACCTFILTER-ISVALID              VALUE '1'.                   \n           88  FLG-ACCTFILTER-BLANK                VALUE ' '.                   \n         05  WS-EDIT-CARD-FLAG                     PIC X(1).                    \n           88  FLG-CARDFILTER-NOT-OK               VALUE '0'.                   \n           88  FLG-CARDFILTER-ISVALID             VALUE '1'.                    \n           88  FLG-CARDFILTER-BLANK                VALUE ' '.                   \n         05  WS-RETURN-FLAG                        PIC X(1).                    \n           88  WS-RETURN-FLAG-OFF                  VALUE LOW-VALUES.            \n           88  WS-RETURN-FLAG-ON                   VALUE '1'.                   \n         05  WS-PFK-FLAG                           PIC X(1).                    \n           88  PFK-VALID                           VALUE '0'.                   \n           88  PFK-INVALID                         VALUE '1'.                   \n      ******************************************************************        \n      * Output edits                                                            \n      ******************************************************************        \n         05 CICS-OUTPUT-EDIT-VARS.                                              \n           10  CARD-ACCT-ID-X                      PIC X(11).                   \n           10  CARD-ACCT-ID-N REDEFINES CARD-ACCT-ID-X                          \n                                                   PIC 9(11).                   \n           10  CARD-CVV-CD-X                       PIC X(03).                   \n           10  CARD-CVV-CD-N REDEFINES  CARD-CVV-CD-X                           \n                                                   PIC 9(03).                   \n           10  CARD-CARD-NUM-X                     PIC X(16).                   \n           10  CARD-CARD-NUM-N REDEFINES  CARD-CARD-NUM-X                       \n                                                   PIC 9(16).                   \n           10  CARD-NAME-EMBOSSED-X                PIC X(50).                   \n           10  CARD-STATUS-X                       PIC X.                       \n           10  CARD-EXPIRAION-DATE-X               PIC X(10).                   \n           10  FILLER REDEFINES CARD-EXPIRAION-DATE-X.                          \n               20 CARD-EXPIRY-YEAR                 PIC X(4).                    \n               20 FILLER                           PIC X(1).                    \n               20 CARD-EXPIRY-MONTH                PIC X(2).                    \n               20 FILLER                           PIC X(1).                    \n               20 CARD-EXPIRY-DAY                  PIC X(2).                    \n           10  CARD-EXPIRAION-DATE-N REDEFINES                                  \n               CARD-EXPIRAION-DATE-X               PIC 9(10).                   \n                                                                                \n      ******************************************************************        \n      *      File and data Handling                                             \n      ******************************************************************        \n         05  WS-CARD-RID.                                                       \n           10  WS-CARD-RID-CARDNUM                 PIC X(16).                   \n           10  WS-CARD-RID-ACCT-ID                 PIC 9(11).                   \n           10  WS-CARD-RID-ACCT-ID-X REDEFINES                                  \n                  WS-CARD-RID-ACCT-ID              PIC X(11).                   \n         05  WS-FILE-ERROR-MESSAGE.                                             \n           10  FILLER                              PIC X(12)                    \n                                                   VALUE 'File Error: '.        \n           10  ERROR-OPNAME                        PIC X(8)                     \n                                                   VALUE SPACES.                \n           10  FILLER                              PIC X(4)                     \n                                                   VALUE ' on '.                \n           10  ERROR-FILE                          PIC X(9)                     \n                                                   VALUE SPACES.                \n           10  FILLER                              PIC X(15)                    \n                                                   VALUE                        \n                                                   ' returned RESP '.           \n           10  ERROR-RESP                          PIC X(10)                    \n                                                   VALUE SPACES.                \n           10  FILLER                              PIC X(7)                     \n                                                   VALUE ',RESP2 '.             \n           10  ERROR-RESP2                         PIC X(10)                    \n                                                   VALUE SPACES.                \n          10  FILLER                               PIC X(5)                     \n                                                   VALUE SPACES.                \n      ******************************************************************        \n      *      Output Message Construction                                        \n      ******************************************************************        \n         05  WS-LONG-MSG                           PIC X(500).                  \n         05  WS-INFO-MSG                           PIC X(40).                   \n           88  WS-NO-INFO-MESSAGE                 VALUES                        \n                                                  SPACES LOW-VALUES.            \n           88  FOUND-CARDS-FOR-ACCOUNT             VALUE                        \n               '   Displaying requested details'.                               \n           88  WS-PROMPT-FOR-INPUT                 VALUE                        \n               'Please enter Account and Card Number'.                          \n                                                                                \n         05  WS-RETURN-MSG                         PIC X(75).                   \n           88  WS-RETURN-MSG-OFF                   VALUE SPACES.                \n           88  WS-EXIT-MESSAGE                     VALUE                        \n               'PF03 pressed.Exiting              '.                            \n           88  WS-PROMPT-FOR-ACCT                  VALUE                        \n               'Account number not provided'.                                   \n           88  WS-PROMPT-FOR-CARD                  VALUE                        \n               'Card number not provided'.                                      \n           88  NO-SEARCH-CRITERIA-RECEIVED         VALUE                        \n               'No input received'.                                             \n           88  SEARCHED-ACCT-ZEROES                VALUE                        \n               'Account number must be a non zero 11 digit number'.             \n           88  SEARCHED-ACCT-NOT-NUMERIC           VALUE                        \n               'Account number must be a non zero 11 digit number'.             \n           88  SEARCHED-CARD-NOT-NUMERIC           VALUE                        \n               'Card number if supplied must be a 16 digit number'.             \n                                                                                \n           88  DID-NOT-FIND-ACCT-IN-CARDXREF       VALUE                        \n               'Did not find this account in cards database'.                   \n           88  DID-NOT-FIND-ACCTCARD-COMBO         VALUE                        \n               'Did not find cards for this search condition'.                  \n           88  XREF-READ-ERROR                     VALUE                        \n               'Error reading Card Data File'.                                  \n           88  CODING-TO-BE-DONE                   VALUE                        \n               'Looks Good.... so far'.                                         \n      *******************************","comments":"","copy_references":["CVCRD01Y","COCOM01Y","DFHBMSCA","DFHAID","COTTL01Y","COCRDSL","CSDAT01Y","CSMSG01Y","CSMSG02Y","CSUSR01Y","CVACT02Y","CVCUS01Y"],"calls_to":[]},{"file_path":"/Users/ianzepp/github/gauntlet/gauntlet-week-3/aws-mainframe-modernization-carddemo/app/cbl/COCRDLIC.cbl","file_name":"COCRDLIC.cbl","file_type":"cbl","name":"1400-SETUP-MESSAGE","start_line":895.0,"end_line":932.0,"score":0.28494128584861755,"chunk_type":"paragraph","preamble":"File: COCRDLIC.cbl\nProgram: COCRDLIC - Business logic - List Credit Cards\nParagraph: 1400-SETUP-MESSAGE (lines 895-932)\nReferences: COPY CVCRD01Y, COPY COCOM01Y, COPY DFHBMSCA, COPY DFHAID, COPY COTTL01Y, COPY COCRDLI, COPY CSDAT01Y, COPY CSMSG01Y, COPY CSUSR01Y, COPY CVACT02Y","summary":"paragraph 1400-SETUP-MESSAGE in COCRDLIC.cbl. uses COPY refs: CVCRD01Y, COCOM01Y, DFHBMSCA, DFHAID....","content":"       1400-SETUP-MESSAGE.                                                      \n      *    SETUP MESSAGE                                                        \n           EVALUATE TRUE                                                        \n                WHEN FLG-ACCTFILTER-NOT-OK                                      \n                WHEN FLG-CARDFILTER-NOT-OK                                      \n                  CONTINUE                                                      \n                WHEN CCARD-AID-PFK07                                            \n                    AND CA-FIRST-PAGE                                           \n                  MOVE 'NO PREVIOUS PAGES TO DISPLAY'                           \n                  TO WS-ERROR-MSG                                               \n                WHEN CCARD-AID-PFK08                                            \n                 AND CA-NEXT-PAGE-NOT-EXISTS                                    \n                 AND CA-LAST-PAGE-SHOWN                                         \n                  MOVE 'NO MORE PAGES TO DISPLAY'                               \n                  TO WS-ERROR-MSG                                               \n                WHEN CCARD-AID-PFK08                                            \n                 AND CA-NEXT-PAGE-NOT-EXISTS                                    \n                  SET WS-INFORM-REC-ACTIONS TO TRUE                             \n                  IF  CA-LAST-PAGE-NOT-SHOWN                                    \n                  AND CA-NEXT-PAGE-NOT-EXISTS                                   \n                      SET CA-LAST-PAGE-SHOWN TO TRUE                            \n                  END-IF                                                        \n                WHEN WS-NO-INFO-MESSAGE                                         \n                WHEN CA-NEXT-PAGE-EXISTS                                        \n                  SET WS-INFORM-REC-ACTIONS TO TRUE                             \n                WHEN OTHER                                                      \n                   SET WS-NO-INFO-MESSAGE TO TRUE                               \n           END-EVALUATE                                                         \n                                                                                \n           MOVE WS-ERROR-MSG          TO ERRMSGO OF CCRDLIAO                    \n                                                                                \n           IF  NOT WS-NO-INFO-MESSAGE                                           \n           AND NOT WS-NO-RECORDS-FOUND                                          \n              MOVE WS-INFO-MSG        TO INFOMSGO OF CCRDLIAO                   \n              MOVE DFHNEUTR           TO INFOMSGC OF CCRDLIAO                   \n           END-IF                                                               \n                                                                                \n           .                                                                    ","comments":"","copy_references":["CVCRD01Y","COCOM01Y","DFHBMSCA","DFHAID","COTTL01Y","COCRDLI","CSDAT01Y","CSMSG01Y","CSUSR01Y","CVACT02Y"],"calls_to":[]},{"file_path":"/Users/ianzepp/github/gauntlet/gauntlet-week-3/aws-mainframe-modernization-carddemo/app/app-authorization-ims-db2-mq/cbl/COPAUS0C.cbl","file_name":"COPAUS0C.cbl","file_type":"cbl","name":"GETACCTDATA-BYACCT","start_line":865.0,"end_line":914.0,"score":0.28243517875671387,"chunk_type":"paragraph","preamble":"File: COPAUS0C.cbl\nProgram: COPAUS0C - CICS COBOL IMS BMS Program - Summary View of Authoriation Messages\nParagraph: GETACCTDATA-BYACCT (lines 865-914)\nReferences: COPY COCOM01Y, COPY COPAU00, COPY COTTL01Y, COPY CSDAT01Y, COPY CSMSG01Y, COPY CSMSG02Y, COPY CVACT01Y, COPY CVACT02Y, COPY CVACT03Y, COPY CVCUS01Y, COPY CIPAUSMY, COPY CIPAUDTY, COPY DFHAID, COPY DFHBMSCA\nCalls: PERFORM SEND-PAULST-SCREEN","summary":"paragraph GETACCTDATA-BYACCT in COPAUS0C.cbl. uses COPY refs: COCOM01Y, COPAU00, COTTL01Y, CSDAT01Y.... invokes: PERFORM SEND-PAULST-SCREEN.","content":"       GETACCTDATA-BYACCT.\n      *****************************************************************\n\n           MOVE XREF-ACCT-ID            TO WS-CARD-RID-ACCT-ID\n           EXEC CICS READ\n                DATASET   (WS-ACCTFILENAME)\n                RIDFLD    (WS-CARD-RID-ACCT-ID-X)\n                KEYLENGTH (LENGTH OF WS-CARD-RID-ACCT-ID-X)\n                INTO      (ACCOUNT-RECORD)\n                LENGTH    (LENGTH OF ACCOUNT-RECORD)\n                RESP      (WS-RESP-CD)\n                RESP2     (WS-REAS-CD)\n           END-EXEC\n\n           EVALUATE WS-RESP-CD\n               WHEN DFHRESP(NORMAL)\n                  continue\n               WHEN DFHRESP(NOTFND)\n                  MOVE WS-RESP-CD        TO WS-RESP-CD-DIS\n                  MOVE WS-REAS-CD        TO WS-REAS-CD-DIS\n\n                  STRING\n                  'Account:'\n                   WS-CARD-RID-ACCT-ID-X\n                  ' not found in ACCT file. Resp:' WS-RESP-CD-DIS\n                  ' Reas:' WS-REAS-CD-DIS\n                  DELIMITED BY SIZE\n                  INTO WS-MESSAGE\n                  END-STRING\n                  MOVE -1       TO ACCTIDL OF COPAU0AI\n                  PERFORM SEND-PAULST-SCREEN\n               WHEN OTHER\n                  MOVE 'Y'     TO WS-ERR-FLG\n                  MOVE WS-RESP-CD        TO WS-RESP-CD-DIS\n                  MOVE WS-REAS-CD        TO WS-REAS-CD-DIS\n\n                  STRING\n                  'Account:'\n                   WS-CARD-RID-ACCT-ID-X\n                  ' System error while reading ACCT file. Resp:'\n                  WS-RESP-CD-DIS ' Reas:' WS-REAS-CD-DIS\n                  DELIMITED BY SIZE\n                  INTO WS-MESSAGE\n                  END-STRING\n                  MOVE -1       TO ACCTIDL OF COPAU0AI\n                  PERFORM SEND-PAULST-SCREEN\n           END-EVALUATE\n           .\n\n      *****************************************************************","comments":"","copy_references":["COCOM01Y","COPAU00","COTTL01Y","CSDAT01Y","CSMSG01Y","CSMSG02Y","CVACT01Y","CVACT02Y","CVACT03Y","CVCUS01Y","CIPAUSMY","CIPAUDTY","DFHAID","DFHBMSCA"],"calls_to":["PERFORM SEND-PAULST-SCREEN"]}]}