{"query":"How does READ-ACCOUNT-RECORD work?","top_k_built":10,"results":[{"file_path":"/Users/ianzepp/github/gauntlet/gauntlet-week-3/aws-mainframe-modernization-carddemo/app/cbl/CBTRN01C.cbl","file_name":"CBTRN01C.cbl","file_type":"cbl","name":"3000-READ-ACCOUNT","start_line":241.0,"end_line":251.0,"score":0.32808470726013184,"chunk_type":"paragraph","preamble":"File: CBTRN01C.cbl\nProgram: CBTRN01C - BATCH COBOL Program - Post the records from daily transaction file.\nParagraph: 3000-READ-ACCOUNT (lines 241-251)\nReferences: COPY CVTRA06Y, COPY CVCUS01Y, COPY CVACT03Y, COPY CVACT02Y, COPY CVACT01Y, COPY CVTRA05Y","summary":"paragraph 3000-READ-ACCOUNT in CBTRN01C.cbl. uses COPY refs: CVTRA06Y, CVCUS01Y, CVACT03Y, CVACT02Y.... comment hint: ---------------------------------------------------------------*.","content":"       3000-READ-ACCOUNT.\n           MOVE ACCT-ID TO FD-ACCT-ID\n           READ ACCOUNT-FILE RECORD INTO ACCOUNT-RECORD\n           KEY IS FD-ACCT-ID\n                INVALID KEY\n                  DISPLAY 'INVALID ACCOUNT NUMBER FOUND'\n                  MOVE 4 TO WS-ACCT-READ-STATUS\n                NOT INVALID KEY\n                  DISPLAY 'SUCCESSFUL READ OF ACCOUNT FILE'\n           END-READ.\n      *---------------------------------------------------------------*","comments":"---------------------------------------------------------------*","copy_references":["CVTRA06Y","CVCUS01Y","CVACT03Y","CVACT02Y","CVACT01Y","CVTRA05Y"],"calls_to":[]},{"file_path":"/Users/ianzepp/github/gauntlet/gauntlet-week-3/aws-mainframe-modernization-carddemo/app/cbl/COACTUPC.cbl","file_name":"COACTUPC.cbl","file_type":"cbl","name":"9000-READ-ACCT, 9000-READ-ACCT-EXIT","start_line":3608.0,"end_line":3649.0,"score":0.3207176625728607,"chunk_type":"paragraph","preamble":"File: COACTUPC.cbl\nProgram: COACTUPC - Business logic - Accept and process ACCOUNT UPDATE\nParagraph: 9000-READ-ACCT, 9000-READ-ACCT-EXIT (lines 3608-3649)\nReferences: COPY CVCRD01Y, COPY CSLKPCDY, COPY DFHBMSCA, COPY DFHAID, COPY COTTL01Y, COPY COACTUP, COPY CSDAT01Y, COPY CSMSG01Y, COPY CSMSG02Y, COPY CSUSR01Y, COPY CVACT01Y, COPY CVACT03Y, COPY CVCUS01Y, COPY COCOM01Y, COPY CSSETATY, COPY CSUTLDPY\nCalls: PERFORM 9200-GETCARDXREF-BYACCT, PERFORM 9300-GETACCTDATA-BYACCT, PERFORM 9400-GETCUSTDATA-BYCUST, PERFORM 9500-STORE-FETCHED-DATA","summary":"paragraph 9000-READ-ACCT, 9000-READ-ACCT-EXIT in COACTUPC.cbl. uses COPY refs: CVCRD01Y, CSLKPCDY, DFHBMSCA, DFHAID.... invokes: PERFORM 9200-GETCARDXREF-BYACCT, PERFORM 9300-GETACCTDATA-BYACCT, PERFORM 9400-GETCUSTDATA-BYCUST, PERFORM 9500-STORE-FETCHED-DATA.","content":"       9000-READ-ACCT.\n\n           INITIALIZE ACUP-OLD-DETAILS\n\n           SET  WS-NO-INFO-MESSAGE      TO TRUE\n\n           MOVE CC-ACCT-ID              TO ACUP-OLD-ACCT-ID\n                                           WS-CARD-RID-ACCT-ID\n\n           PERFORM 9200-GETCARDXREF-BYACCT\n              THRU 9200-GETCARDXREF-BYACCT-EXIT\n\n           IF FLG-ACCTFILTER-NOT-OK\n              GO TO 9000-READ-ACCT-EXIT\n           END-IF\n\n           PERFORM 9300-GETACCTDATA-BYACCT\n              THRU 9300-GETACCTDATA-BYACCT-EXIT\n\n           IF DID-NOT-FIND-ACCT-IN-ACCTDAT\n              GO TO 9000-READ-ACCT-EXIT\n           END-IF\n\n           MOVE CDEMO-CUST-ID TO WS-CARD-RID-CUST-ID\n\n           PERFORM 9400-GETCUSTDATA-BYCUST\n              THRU 9400-GETCUSTDATA-BYCUST-EXIT\n\n           IF DID-NOT-FIND-CUST-IN-CUSTDAT\n              GO TO 9000-READ-ACCT-EXIT\n           END-IF\n\n\n\n           PERFORM 9500-STORE-FETCHED-DATA\n              THRU 9500-STORE-FETCHED-DATA-EXIT\n           .\n\n\n       9000-READ-ACCT-EXIT.\n           EXIT\n           .","comments":"","copy_references":["CVCRD01Y","CSLKPCDY","DFHBMSCA","DFHAID","COTTL01Y","COACTUP","CSDAT01Y","CSMSG01Y","CSMSG02Y","CSUSR01Y","CVACT01Y","CVACT03Y","CVCUS01Y","COCOM01Y","CSSETATY","CSUTLDPY"],"calls_to":["PERFORM 9200-GETCARDXREF-BYACCT","PERFORM 9300-GETACCTDATA-BYACCT","PERFORM 9400-GETCUSTDATA-BYCUST","PERFORM 9500-STORE-FETCHED-DATA"]},{"file_path":"/Users/ianzepp/github/gauntlet/gauntlet-week-3/aws-mainframe-modernization-carddemo/app/cbl/COCRDLIC.cbl","file_name":"COCRDLIC.cbl","file_type":"cbl","name":"9100-READ-BACKWARDS","start_line":1264.0,"end_line":1373.0,"score":0.31436511874198914,"chunk_type":"paragraph","preamble":"File: COCRDLIC.cbl\nProgram: COCRDLIC - Business logic - List Credit Cards\nParagraph: 9100-READ-BACKWARDS (lines 1264-1373)\nReferences: COPY CVCRD01Y, COPY COCOM01Y, COPY DFHBMSCA, COPY DFHAID, COPY COTTL01Y, COPY COCRDLI, COPY CSDAT01Y, COPY CSMSG01Y, COPY CSUSR01Y, COPY CVACT02Y\nCalls: PERFORM 9500-FILTER-RECORDS","summary":"paragraph 9100-READ-BACKWARDS in COCRDLIC.cbl. uses COPY refs: CVCRD01Y, COCOM01Y, DFHBMSCA, DFHAID.... invokes: PERFORM 9500-FILTER-RECORDS.","content":"       9100-READ-BACKWARDS.                                                     \n                                                                                \n           MOVE LOW-VALUES           TO WS-ALL-ROWS                             \n                                                                                \n           MOVE WS-CA-FIRST-CARDKEY  TO WS-CA-LAST-CARDKEY                      \n                                                                                \n      *****************************************************************         \n      *    Start Browse                                                         \n      *****************************************************************         \n           EXEC CICS STARTBR                                                    \n                DATASET(LIT-CARD-FILE)                                          \n                RIDFLD(WS-CARD-RID-CARDNUM)                                     \n                KEYLENGTH(LENGTH OF WS-CARD-RID-CARDNUM)                        \n                GTEQ                                                            \n                RESP(WS-RESP-CD)                                                \n                RESP2(WS-REAS-CD)                                               \n           END-EXEC                                                             \n      *****************************************************************         \n      *    Loop through records and fetch max screen records                    \n      *****************************************************************         \n           COMPUTE WS-SCRN-COUNTER =                                            \n                                   WS-MAX-SCREEN-LINES + 1                      \n           END-COMPUTE                                                          \n           SET CA-NEXT-PAGE-EXISTS    TO TRUE                                   \n           SET MORE-RECORDS-TO-READ   TO TRUE                                   \n                                                                                \n      *****************************************************************         \n      *    Now we show the records from previous set.                           \n      *****************************************************************         \n                                                                                \n           EXEC CICS READPREV                                                   \n                DATASET(LIT-CARD-FILE)                                          \n                INTO (CARD-RECORD)                                              \n                LENGTH(LENGTH OF CARD-RECORD)                                   \n                RIDFLD(WS-CARD-RID-CARDNUM)                                     \n                KEYLENGTH(LENGTH OF WS-CARD-RID-CARDNUM)                        \n                RESP(WS-RESP-CD)                                                \n                RESP2(WS-REAS-CD)                                               \n           END-EXEC                                                             \n                                                                                \n           EVALUATE WS-RESP-CD                                                  \n               WHEN DFHRESP(NORMAL)                                             \n               WHEN DFHRESP(DUPREC)                                             \n                   SUBTRACT 1          FROM WS-SCRN-COUNTER                     \n               WHEN OTHER                                                       \n      *           This is some kind of error. Change to END BR                  \n      *           And exit                                                      \n                  SET READ-LOOP-EXIT             TO TRUE                        \n                  MOVE 'READ'                     TO ERROR-OPNAME               \n                  MOVE LIT-CARD-FILE              TO ERROR-FILE                 \n                  MOVE WS-RESP-CD                 TO ERROR-RESP                 \n                  MOVE WS-REAS-CD                 TO ERROR-RESP2                \n                  MOVE WS-FILE-ERROR-MESSAGE      TO WS-ERROR-MSG               \n                  GO TO 9100-READ-BACKWARDS-EXIT                                \n           END-EVALUATE                                                         \n                                                                                \n           PERFORM UNTIL READ-LOOP-EXIT                                         \n                                                                                \n           EXEC CICS READPREV                                                   \n                DATASET(LIT-CARD-FILE)                                          \n                INTO (CARD-RECORD)                                              \n                LENGTH(LENGTH OF CARD-RECORD)                                   \n                RIDFLD(WS-CARD-RID-CARDNUM)                                     \n                KEYLENGTH(LENGTH OF WS-CARD-RID-CARDNUM)                        \n                RESP(WS-RESP-CD)                                                \n                RESP2(WS-REAS-CD)                                               \n           END-EXEC                                                             \n                                                                                \n           EVALUATE WS-RESP-CD                                                  \n               WHEN DFHRESP(NORMAL)                                             \n               WHEN DFHRESP(DUPREC)                                             \n                   PERFORM 9500-FILTER-RECORDS                                  \n                      THRU 9500-FILTER-RECORDS-EXIT                             \n                   IF WS-DONOT-EXCLUDE-THIS-RECORD                              \n                      MOVE CARD-NUM                                             \n                                  TO WS-ROW-CARD-NUM(WS-SCRN-COUNTER)           \n                      MOVE CARD-ACCT-ID                                         \n                                  TO WS-ROW-ACCTNO(WS-SCRN-COUNTER)             \n                      MOVE CARD-ACTIVE-STATUS                                   \n                                  TO                                            \n                                  WS-ROW-CARD-STATUS(WS-SCRN-COUNTER)           \n                                                                                \n                      SUBTRACT 1  FROM WS-SCRN-COUNTER                          \n                      IF WS-SCRN-COUNTER = 0                                    \n                         SET READ-LOOP-EXIT  TO TRUE                            \n                                                                                \n                         MOVE CARD-ACCT-ID                                      \n                                  TO WS-CA-FIRST-CARD-ACCT-ID                   \n                         MOVE CARD-NUM                                          \n                                  TO WS-CA-FIRST-CARD-NUM                       \n                      ELSE                                                      \n                         CONTINUE                                               \n                      END-IF                                                    \n                   ELSE                                                         \n                       CONTINUE                                                 \n                   END-IF                                                       \n                                                                                \n               WHEN OTHER                                                       \n      *           This is some kind of error. Change to END BR                  \n      *           And exit                                                      \n                  SET READ-LOOP-EXIT             TO TRUE                        \n                  MOVE 'READ'                     TO ERROR-OPNAME               \n                  MOVE LIT-CARD-FILE              TO ERROR-FILE                 \n                  MOVE WS-RESP-CD                 TO ERROR-RESP                 \n                  MOVE WS-REAS-CD                 TO ERROR-RESP2                \n                  MOVE WS-FILE-ERROR-MESSAGE      TO WS-ERROR-MSG               \n           END-EVALUATE                                                         \n           END-PERFORM                                                          \n           .                                                                    \n                                                                                ","comments":"","copy_references":["CVCRD01Y","COCOM01Y","DFHBMSCA","DFHAID","COTTL01Y","COCRDLI","CSDAT01Y","CSMSG01Y","CSUSR01Y","CVACT02Y"],"calls_to":["PERFORM 9500-FILTER-RECORDS"]},{"file_path":"/Users/ianzepp/github/gauntlet/gauntlet-week-3/aws-mainframe-modernization-carddemo/app/jcl/READACCT.jcl","file_name":"READACCT.jcl","file_type":"jcl","name":"READACCT Header","start_line":1.0,"end_line":21.0,"score":0.31023240089416504,"chunk_type":"jcl_step","preamble":"File: READACCT.jcl\nJCL Header: READACCT (lines 1-21)","summary":"jcl_step READACCT Header in READACCT.jcl.","content":"//READACCT JOB 'READACCT',REGION=8M,CLASS=A,                            JOB05427\n//      MSGCLASS=H,NOTIFY=&SYSUID\n//******************************************************************\n//* Copyright Amazon.com, Inc. or its affiliates.\n//* All Rights Reserved.\n//*\n//* Licensed under the Apache License, Version 2.0 (the \"License\").\n//* You may not use this file except in compliance with the License.\n//* You may obtain a copy of the License at\n//*\n//*    http://www.apache.org/licenses/LICENSE-2.0\n//*\n//* Unless required by applicable law or agreed to in writing,\n//* software distributed under the License is distributed on an\n//* \"AS IS\" BASIS, WITHOUT WARRANTIES OR CONDITIONS OF ANY KIND,\n//* either express or implied. See the License for the specific\n//* language governing permissions and limitations under the License\n//******************************************************************\n//* *******************************************************************\n//* PRE DELETE STEP\n//* *******************************************************************","comments":"","copy_references":[],"calls_to":[]},{"file_path":"/Users/ianzepp/github/gauntlet/gauntlet-week-3/aws-mainframe-modernization-carddemo/app/cbl/COCRDLIC.cbl","file_name":"COCRDLIC.cbl","file_type":"cbl","name":"9000-READ-FORWARD, 9000-READ-FORWARD-EXIT","start_line":1123.0,"end_line":1263.0,"score":0.3034702241420746,"chunk_type":"paragraph","preamble":"File: COCRDLIC.cbl\nProgram: COCRDLIC - Business logic - List Credit Cards\nParagraph: 9000-READ-FORWARD, 9000-READ-FORWARD-EXIT (lines 1123-1263)\nReferences: COPY CVCRD01Y, COPY COCOM01Y, COPY DFHBMSCA, COPY DFHAID, COPY COTTL01Y, COPY COCRDLI, COPY CSDAT01Y, COPY CSMSG01Y, COPY CSUSR01Y, COPY CVACT02Y\nCalls: PERFORM 9500-FILTER-RECORDS","summary":"paragraph 9000-READ-FORWARD, 9000-READ-FORWARD-EXIT in COCRDLIC.cbl. uses COPY refs: CVCRD01Y, COCOM01Y, DFHBMSCA, DFHAID.... invokes: PERFORM 9500-FILTER-RECORDS.","content":"       9000-READ-FORWARD.                                                       \n           MOVE LOW-VALUES           TO WS-ALL-ROWS                             \n                                                                                \n      *****************************************************************         \n      *    Start Browse                                                         \n      *****************************************************************         \n           EXEC CICS STARTBR                                                    \n                DATASET(LIT-CARD-FILE)                                          \n                RIDFLD(WS-CARD-RID-CARDNUM)                                     \n                KEYLENGTH(LENGTH OF WS-CARD-RID-CARDNUM)                        \n                GTEQ                                                            \n                RESP(WS-RESP-CD)                                                \n                RESP2(WS-REAS-CD)                                               \n           END-EXEC                                                             \n      *****************************************************************         \n      *    Loop through records and fetch max screen records                    \n      *****************************************************************         \n           MOVE ZEROES TO WS-SCRN-COUNTER                                       \n           SET CA-NEXT-PAGE-EXISTS    TO TRUE                                   \n           SET MORE-RECORDS-TO-READ   TO TRUE                                   \n                                                                                \n           PERFORM UNTIL READ-LOOP-EXIT                                         \n                                                                                \n           EXEC CICS READNEXT                                                   \n                DATASET(LIT-CARD-FILE)                                          \n                INTO (CARD-RECORD)                                              \n                LENGTH(LENGTH OF CARD-RECORD)                                   \n                RIDFLD(WS-CARD-RID-CARDNUM)                                     \n                KEYLENGTH(LENGTH OF WS-CARD-RID-CARDNUM)                        \n                RESP(WS-RESP-CD)                                                \n                RESP2(WS-REAS-CD)                                               \n           END-EXEC                                                             \n                                                                                \n           EVALUATE WS-RESP-CD                                                  \n               WHEN DFHRESP(NORMAL)                                             \n               WHEN DFHRESP(DUPREC)                                             \n                   PERFORM 9500-FILTER-RECORDS                                  \n                      THRU 9500-FILTER-RECORDS-EXIT                             \n                                                                                \n                   IF WS-DONOT-EXCLUDE-THIS-RECORD                              \n                      ADD 1             TO WS-SCRN-COUNTER                      \n                                                                                \n                      MOVE CARD-NUM     TO WS-ROW-CARD-NUM(                     \n                      WS-SCRN-COUNTER)                                          \n                      MOVE CARD-ACCT-ID TO                                      \n                      WS-ROW-ACCTNO(WS-SCRN-COUNTER)                            \n                      MOVE CARD-ACTIVE-STATUS                                   \n                                        TO WS-ROW-CARD-STATUS(                  \n                                        WS-SCRN-COUNTER)                        \n                                                                                \n                      IF WS-SCRN-COUNTER = 1                                    \n                         MOVE CARD-ACCT-ID                                      \n                                        TO WS-CA-FIRST-CARD-ACCT-ID             \n                         MOVE CARD-NUM  TO WS-CA-FIRST-CARD-NUM                 \n                         IF   WS-CA-SCREEN-NUM = 0                              \n                           ADD   +1     TO WS-CA-SCREEN-NUM                     \n                         ELSE                                                   \n                           CONTINUE                                             \n                         END-IF                                                 \n                      ELSE                                                      \n                         CONTINUE                                               \n                      END-IF                                                    \n                   ELSE                                                         \n                       CONTINUE                                                 \n                   END-IF                                                       \n      ******************************************************************        \n      *            Max Screen size                                              \n      ******************************************************************        \n                   IF WS-SCRN-COUNTER = WS-MAX-SCREEN-LINES                     \n                      SET READ-LOOP-EXIT  TO TRUE                               \n                                                                                \n                      MOVE CARD-ACCT-ID     TO WS-CA-LAST-CARD-ACCT-ID          \n                      MOVE CARD-NUM         TO WS-CA-LAST-CARD-NUM              \n                                                                                \n                      EXEC CICS READNEXT                                        \n                        DATASET(LIT-CARD-FILE)                                  \n                        INTO (CARD-RECORD)                                      \n                        LENGTH(LENGTH OF CARD-RECORD)                           \n                        RIDFLD(WS-CARD-RID-CARDNUM)                             \n                        KEYLENGTH(LENGTH OF WS-CARD-RID-CARDNUM)                \n                        RESP(WS-RESP-CD)                                        \n                        RESP2(WS-REAS-CD)                                       \n                      END-EXEC                                                  \n                                                                                \n                      EVALUATE WS-RESP-CD                                       \n                         WHEN DFHRESP(NORMAL)                                   \n                         WHEN DFHRESP(DUPREC)                                   \n                              SET CA-NEXT-PAGE-EXISTS                           \n                                                TO TRUE                         \n                              MOVE CARD-ACCT-ID TO                              \n                                   WS-CA-LAST-CARD-ACCT-ID                      \n                              MOVE CARD-NUM     TO WS-CA-LAST-CARD-NUM          \n                        WHEN DFHRESP(ENDFILE)                                   \n                            SET CA-NEXT-PAGE-NOT-EXISTS     TO TRUE             \n                                                                                \n                            IF WS-ERROR-MSG-OFF                                 \n                                MOVE 'NO MORE RECORDS TO SHOW'                  \n                                                TO WS-ERROR-MSG                 \n                            END-IF                                              \n                            WHEN OTHER                                          \n      *                     This is some kind of error. Change to END BR        \n      *                     And exit                                            \n                            SET READ-LOOP-EXIT      TO TRUE                     \n                            MOVE 'READ'              TO ERROR-OPNAME            \n                            MOVE LIT-CARD-FILE       TO ERROR-FILE              \n                            MOVE WS-RESP-CD          TO ERROR-RESP              \n                            MOVE WS-REAS-CD          TO ERROR-RESP2             \n                          MOVE WS-FILE-ERROR-MESSAGE TO WS-ERROR-MSG            \n                      END-EVALUATE                                              \n                  END-IF                                                        \n               WHEN DFHRESP(ENDFILE)                                            \n                  SET READ-LOOP-EXIT              TO TRUE                       \n                  SET CA-NEXT-PAGE-NOT-EXISTS     TO TRUE                       \n                  MOVE CARD-ACCT-ID     TO WS-CA-LAST-CARD-ACCT-ID              \n                  MOVE CARD-NUM         TO WS-CA-LAST-CARD-NUM                  \n                  IF WS-ERROR-MSG-OFF                                           \n                     MOVE 'NO MORE RECORDS TO SHOW'  TO WS-ERROR-MSG            \n                  END-IF                                                        \n                  IF WS-CA-SCREEN-NUM = 1                                       \n                  AND WS-SCRN-COUNTER = 0                                       \n      *               MOVE 'NO RECORDS TO SHOW'  TO WS-ERROR-MSG                \n                      SET WS-NO-RECORDS-FOUND    TO TRUE                        \n                  END-IF                                                        \n               WHEN OTHER            ","comments":"","copy_references":["CVCRD01Y","COCOM01Y","DFHBMSCA","DFHAID","COTTL01Y","COCRDLI","CSDAT01Y","CSMSG01Y","CSUSR01Y","CVACT02Y"],"calls_to":["PERFORM 9500-FILTER-RECORDS"]},{"file_path":"/Users/ianzepp/github/gauntlet/gauntlet-week-3/aws-mainframe-modernization-carddemo/app/jcl/READACCT.jcl","file_name":"READACCT.jcl","file_type":"jcl","name":"PREDEL","start_line":22.0,"end_line":31.0,"score":0.2988170087337494,"chunk_type":"jcl_step","preamble":"File: READACCT.jcl\nJCL Step: PREDEL (lines 22-31)","summary":"jcl_step PREDEL in READACCT.jcl.","content":"//PREDEL  EXEC PGM=IEFBR14\n//DD01     DD DSN=AWS.M2.CARDDEMO.ACCTDATA.PSCOMP,\n//            DISP=(MOD,DELETE,DELETE)\n//DD02     DD DSN=AWS.M2.CARDDEMO.ACCTDATA.ARRYPS,\n//            DISP=(MOD,DELETE,DELETE)\n//DD03     DD DSN=AWS.M2.CARDDEMO.ACCTDATA.VBPS,\n//            DISP=(MOD,DELETE,DELETE)\n//* *******************************************************************\n//* RUN THE PROGRAM THAT READS THE ACCOUNT MASTER VSAM FILE\n//* *******************************************************************","comments":"","copy_references":[],"calls_to":[]},{"file_path":"/Users/ianzepp/github/gauntlet/gauntlet-week-3/aws-mainframe-modernization-carddemo/app/cbl/CBACT01C.cbl","file_name":"CBACT01C.cbl","file_type":"cbl","name":"1575-WRITE-VB2-RECORD","start_line":302.0,"end_line":316.0,"score":0.2969024181365967,"chunk_type":"paragraph","preamble":"File: CBACT01C.cbl\nProgram: CBACT01C - BATCH COBOL Program - READ THE ACCOUNT FILE AND WRITE INTO FILES.\nParagraph: 1575-WRITE-VB2-RECORD (lines 302-316)\nReferences: COPY CVACT01Y, COPY CODATECN\nCalls: PERFORM 9910-DISPLAY-IO-STATUS, PERFORM 9999-ABEND-PROGRAM","summary":"paragraph 1575-WRITE-VB2-RECORD in CBACT01C.cbl. uses COPY refs: CVACT01Y, CODATECN. invokes: PERFORM 9910-DISPLAY-IO-STATUS, PERFORM 9999-ABEND-PROGRAM. comment hint: ---------------------------------------------------------------*.","content":"       1575-WRITE-VB2-RECORD.\n           MOVE 39 TO WS-RECD-LEN.\n           MOVE VBRC-REC2 TO VBR-REC(1:WS-RECD-LEN).\n           WRITE VBR-REC.\n\n           IF VBRCFILE-STATUS NOT = '00'\n                        AND VBRCFILE-STATUS NOT = '10'\n              DISPLAY 'ACCOUNT FILE WRITE STATUS IS:'\n                                        VBRCFILE-STATUS\n              MOVE VBRCFILE-STATUS TO IO-STATUS\n              PERFORM 9910-DISPLAY-IO-STATUS\n              PERFORM 9999-ABEND-PROGRAM\n           END-IF.\n           EXIT.\n      *---------------------------------------------------------------*","comments":"---------------------------------------------------------------*","copy_references":["CVACT01Y","CODATECN"],"calls_to":["PERFORM 9910-DISPLAY-IO-STATUS","PERFORM 9999-ABEND-PROGRAM"]},{"file_path":"/Users/ianzepp/github/gauntlet/gauntlet-week-3/aws-mainframe-modernization-carddemo/app/cbl/CBACT01C.cbl","file_name":"CBACT01C.cbl","file_type":"cbl","name":"1000-ACCTFILE-GET-NEXT","start_line":165.0,"end_line":199.0,"score":0.29302167892456055,"chunk_type":"paragraph","preamble":"File: CBACT01C.cbl\nProgram: CBACT01C - BATCH COBOL Program - READ THE ACCOUNT FILE AND WRITE INTO FILES.\nParagraph: 1000-ACCTFILE-GET-NEXT (lines 165-199)\nReferences: COPY CVACT01Y, COPY CODATECN\nCalls: PERFORM 1100-DISPLAY-ACCT-RECORD, PERFORM 1300-POPUL-ACCT-RECORD, PERFORM 1350-WRITE-ACCT-RECORD, PERFORM 1400-POPUL-ARRAY-RECORD, PERFORM 1450-WRITE-ARRY-RECORD, PERFORM 1500-POPUL-VBRC-RECORD, PERFORM 1550-WRITE-VB1-RECORD, PERFORM 1575-WRITE-VB2-RECORD, PERFORM 9910-DISPLAY-IO-STATUS, PERFORM 9999-ABEND-PROGRAM","summary":"paragraph 1000-ACCTFILE-GET-NEXT in CBACT01C.cbl. uses COPY refs: CVACT01Y, CODATECN. invokes: PERFORM 1100-DISPLAY-ACCT-RECORD, PERFORM 1300-POPUL-ACCT-RECORD, PERFORM 1350-WRITE-ACCT-RECORD, PERFORM 1400-POPUL-ARRAY-RECORD.... comment hint: I/O ROUTINES TO ACCESS A KSDS, VSAM DATA SET...               *.","content":"       1000-ACCTFILE-GET-NEXT.\n           READ ACCTFILE-FILE INTO ACCOUNT-RECORD.\n           IF  ACCTFILE-STATUS = '00'\n               MOVE 0 TO APPL-RESULT\n               INITIALIZE ARR-ARRAY-REC\n               PERFORM 1100-DISPLAY-ACCT-RECORD\n               PERFORM 1300-POPUL-ACCT-RECORD\n               PERFORM 1350-WRITE-ACCT-RECORD\n               PERFORM 1400-POPUL-ARRAY-RECORD\n               PERFORM 1450-WRITE-ARRY-RECORD\n               INITIALIZE VBRC-REC1\n               PERFORM 1500-POPUL-VBRC-RECORD\n               PERFORM 1550-WRITE-VB1-RECORD\n               PERFORM 1575-WRITE-VB2-RECORD\n           ELSE\n               IF  ACCTFILE-STATUS = '10'\n                   MOVE 16 TO APPL-RESULT\n               ELSE\n                   MOVE 12 TO APPL-RESULT\n               END-IF\n           END-IF\n           IF  APPL-AOK\n               CONTINUE\n           ELSE\n               IF  APPL-EOF\n                   MOVE 'Y' TO END-OF-FILE\n               ELSE\n                   DISPLAY 'ERROR READING ACCOUNT FILE'\n                   MOVE ACCTFILE-STATUS TO IO-STATUS\n                   PERFORM 9910-DISPLAY-IO-STATUS\n                   PERFORM 9999-ABEND-PROGRAM\n               END-IF\n           END-IF\n           EXIT.\n      *---------------------------------------------------------------*","comments":"\nI/O ROUTINES TO ACCESS A KSDS, VSAM DATA SET...               *\n","copy_references":["CVACT01Y","CODATECN"],"calls_to":["PERFORM 1100-DISPLAY-ACCT-RECORD","PERFORM 1300-POPUL-ACCT-RECORD","PERFORM 1350-WRITE-ACCT-RECORD","PERFORM 1400-POPUL-ARRAY-RECORD","PERFORM 1450-WRITE-ARRY-RECORD","PERFORM 1500-POPUL-VBRC-RECORD","PERFORM 1550-WRITE-VB1-RECORD","PERFORM 1575-WRITE-VB2-RECORD","PERFORM 9910-DISPLAY-IO-STATUS","PERFORM 9999-ABEND-PROGRAM"]},{"file_path":"/Users/ianzepp/github/gauntlet/gauntlet-week-3/aws-mainframe-modernization-carddemo/app/cbl/CBEXPORT.cbl","file_name":"CBEXPORT.cbl","file_type":"cbl","name":"3000-EXPORT-ACCOUNTS","start_line":312.0,"end_line":326.0,"score":0.28648510575294495,"chunk_type":"paragraph","preamble":"File: CBEXPORT.cbl\nProgram: CBEXPORT\nParagraph: 3000-EXPORT-ACCOUNTS (lines 312-326)\nReferences: COPY CVCUS01Y, COPY CVACT01Y, COPY CVACT03Y, COPY CVTRA05Y, COPY CVACT02Y, COPY CVEXPORT\nCalls: PERFORM 3100-READ-ACCOUNT-RECORD, PERFORM 3200-CREATE-ACCOUNT-EXP-REC","summary":"paragraph 3000-EXPORT-ACCOUNTS in CBEXPORT.cbl. uses COPY refs: CVCUS01Y, CVACT01Y, CVACT03Y, CVTRA05Y.... invokes: PERFORM 3100-READ-ACCOUNT-RECORD, PERFORM 3200-CREATE-ACCOUNT-EXP-REC.","content":"       3000-EXPORT-ACCOUNTS.\n      *****************************************************************\n           DISPLAY 'CBEXPORT: Processing account records'\n           \n           PERFORM 3100-READ-ACCOUNT-RECORD\n           \n           PERFORM UNTIL WS-ACCOUNT-EOF\n               PERFORM 3200-CREATE-ACCOUNT-EXP-REC                      \n               PERFORM 3100-READ-ACCOUNT-RECORD\n           END-PERFORM\n           \n           DISPLAY 'CBEXPORT: Accounts exported: ' \n                   WS-ACCOUNT-RECORDS-EXPORTED.\n\n      *****************************************************************","comments":"","copy_references":["CVCUS01Y","CVACT01Y","CVACT03Y","CVTRA05Y","CVACT02Y","CVEXPORT"],"calls_to":["PERFORM 3100-READ-ACCOUNT-RECORD","PERFORM 3200-CREATE-ACCOUNT-EXP-REC"]},{"file_path":"/Users/ianzepp/github/gauntlet/gauntlet-week-3/aws-mainframe-modernization-carddemo/app/cbl/CBACT01C.cbl","file_name":"CBACT01C.cbl","file_type":"cbl","name":"1350-WRITE-ACCT-RECORD","start_line":242.0,"end_line":252.0,"score":0.2841508686542511,"chunk_type":"paragraph","preamble":"File: CBACT01C.cbl\nProgram: CBACT01C - BATCH COBOL Program - READ THE ACCOUNT FILE AND WRITE INTO FILES.\nParagraph: 1350-WRITE-ACCT-RECORD (lines 242-252)\nReferences: COPY CVACT01Y, COPY CODATECN\nCalls: PERFORM 9910-DISPLAY-IO-STATUS, PERFORM 9999-ABEND-PROGRAM","summary":"paragraph 1350-WRITE-ACCT-RECORD in CBACT01C.cbl. uses COPY refs: CVACT01Y, CODATECN. invokes: PERFORM 9910-DISPLAY-IO-STATUS, PERFORM 9999-ABEND-PROGRAM. comment hint: ---------------------------------------------------------------*.","content":"       1350-WRITE-ACCT-RECORD.\n           WRITE OUT-ACCT-REC.\n\n           IF OUTFILE-STATUS NOT = '00' AND OUTFILE-STATUS NOT = '10'\n              DISPLAY 'ACCOUNT FILE WRITE STATUS IS:'  OUTFILE-STATUS\n              MOVE OUTFILE-STATUS  TO IO-STATUS\n              PERFORM 9910-DISPLAY-IO-STATUS\n              PERFORM 9999-ABEND-PROGRAM\n           END-IF.\n           EXIT.\n      *---------------------------------------------------------------*","comments":"---------------------------------------------------------------*","copy_references":["CVACT01Y","CODATECN"],"calls_to":["PERFORM 9910-DISPLAY-IO-STATUS","PERFORM 9999-ABEND-PROGRAM"]}]}